Workbook

Sheet Read me
A1: CALIBRE BY DAFTAR
A2: Calibre Verdict · working file
A3: One workbook per engagement. Complete the sheets in order. Nothing is scored before sheet 01 is locked.
A5: Sheet | B5: What it is for | C5: Rule
A6: 00 Setup | B6: Panel, finalists and engagement dates | C6: Two to five panelists, one of them the hiring lead. Two to six finalists, K1 to K6, in the order received.
A7: 01 Rubric | B7: The criteria, weights and anchors | C7: Four to nine criteria, whole-number weights totalling 100. Locked before any finalist is scored; never changed after the first score.
A8: 02 Scores | B8: Every panelist's score and evidence note | C8: Enter only after every panelist has submitted, or the scoring deadline has passed. Scores are never edited afterwards.
A9: 03 Divergence | B9: The spread across panelists | C9: Calculated. A spread of 2 is a divergence, 3 or 4 a contradiction. Scores of 0 (no evidence) are excluded from the spread.
A10: 04 Calibration | B10: The resolution of every flagged cell | C10: Enter an agreed score and a written reason for each flagged cell. The original scores on sheet 02 stay as they are.
A11: 05 Results | B11: Calibrated scores and the weighted result | C11: Calculated. Entry order only: never sort, colour or label finalists. The weighted result is advisory.
A12: 06 Outcomes | B12: The 90, 180 and 365-day follow-up | C12: Four questions at each checkpoint, recorded by initials only.
A14: Legend
B15: Shaded cells are for entry. Every other value is a formula; do not overwrite it.
A17: Score | B17: Meaning | C17: When to use it
A18: 5 | B18: Strong evidence, exceeds the requirement | C18: Anchor 5 met, evidenced in the record.
A19: 4 | B19: Above the requirement | C19: Between anchors 3 and 5.
A20: 3 | B20: Meets the requirement | C20: Anchor 3 met, evidenced in the record.
A21: 2 | B21: Partially meets | C21: Between anchors 1 and 3.
A22: 1 | B22: Does not meet | C22: Anchor 1 describes the evidence.
A23: 0 | B23: No evidence supplied | C23: Not assessable on the evidence provided. Recorded as a gap, never as a low score, and excluded from the spread.
A25: Evidence basis | B25: Definition
A26: Documented | B26: Written evidence in the file: CV detail, work product, a test result, a reference supplied by the client.
A27: Interview-stated | B27: The candidate said it in interview; not corroborated elsewhere.
A28: Inferred | B28: Not stated; inferred from role titles, tenure or employer. Named as inference in the Verdict.
A29: None | B29: No evidence either way. Score 0 and record the gap.
A31: Example entry
A32: K1 · C2 | B32: Score 3 · Documented · "CV and second interview note of 12 May: owned the monthly close for a five-entity group. Does not establish listed-group reporting." Evidence notes run to at least 40 characters, naming the source and the fact.
A34: Not in scope
B35: Candidate sourcing, interview scheduling, reference checks, offer negotiation
B36: Psychometric, personality, work-style, culture or fit assessment
B37: Automated candidate ranking, or any recommendation generated by a model
B38: The hiring decision itself
A40: Fonts | B40: Set in Lora and Plus Jakarta Sans (both free, SIL Open Font License). Install them, or Excel substitutes another face.
A42: Use statement | B42: Structured hiring advisory for finance roles. Not a psychometric assessment. Does not predict performance. The decision, and its consequences, rest with the employer.

Sheet 00 Setup
A1: CALIBRE BY DAFTAR
A2: 00 · Setup
A3: The panel, the finalists and the dates. Names are used on the working sheets; the Verdict uses initials.
A5: Engagement
B6: Engagement reference
A7: Ref | B7: Panelist | C7: Title | D7: Hiring lead | E7: Email
A8: P1
A9: P2
A10: P3
A11: P4
A12: P5
B13: Panelists named | C13: =COUNTA(B8:B12) -> 0 | D13: =IF(AND(C13>=2,C13<=5,COUNTIF(D8:D12,"Yes")=1),"OK","Needs 2 to 5 panelists and exactly one hiring lead") -> Needs 2 to 5 panelists and exactly one hiring lead
A15: Ref | B15: Initials | C15: Name (purged 90 days after issue) | D15: Notice sent | E15: Source
A16: K1
A17: K2
A18: K3
A19: K4
A20: K5
A21: K6
B22: Finalists named | C22: =COUNTA(B16:B21) -> 0 | D22: =IF(AND(C22>=2,C22<=6),"OK","Needs 2 to 6 finalists") -> Needs 2 to 6 finalists
B24: Date
B25: Rubric locked
B26: Scoring deadline
B27: Calibration session
B28: Verdict issued
B29: Personal data purge due | C29: =IF(C28="","",C28+90)

Sheet 01 Rubric
A1: CALIBRE BY DAFTAR
A2: 01 · Rubric
A3: Amend wording, must or preferred, and weights at intake. Four to nine criteria. Leave unused rows blank. Once locked, nothing here changes.
A5: Locked on | B5: =IF('00 Setup'!C25="","",'00 Setup'!C25)
A7: Ref | B7: Criterion | C7: Must / Preferred | D7: Weight % | E7: Anchor 1: does not meet | F7: Anchor 3: meets | G7: Anchor 5: strong evidence
A8: C1 | B8: Technical accounting and IFRS application | C8: Must | D8: 15 | E8: No evidence of applying a standard beyond routine bookkeeping; cannot name the standards governing the entity's material balances. | F8: Has applied the standards material to this entity (e.g. revenue, leases, impairment) in a prior role and can explain one judgement they made and why. | G8: Has owned a contested technical judgement end to end - position paper, auditor challenge, resolution - and can walk through the alternative treatment they rejected.
A9: C2 | B9: Financial reporting and close ownership | C9: Must | D9: 15 | E9: Has contributed to a close but never owned a timetable or a deliverable date. | F9: Has owned a monthly or quarterly close of comparable size and complexity, including the reconciliations and the reporting pack. | G9: Has owned close end to end and materially improved it - days reduced, adjustments cut, or a first-time consolidation delivered - with numbers they can state.
A10: C3 | B10: Controls, compliance and audit readiness | C10: Must | D10: 12 | E10: Treats controls as an audit request; no evidence of designing or operating one. | F10: Has run an audit as the entity-side owner: PBC list, sample support, auditor queries closed within the timetable. | G10: Has designed or remediated a control that failed, and can describe the failure, the fix, and how they evidenced the fix to the auditor.
A11: C4 | B11: Planning, budgeting and forecasting | C11: Must | D11: 12 | E11: Has populated a budget template but not built the model or owned the assumptions. | F11: Has built and maintained a budget or rolling forecast for the entity, and can explain the two or three assumptions that actually drive it. | G11: Has run a forecast through a decision that mattered - a cut, a raise, a covenant - and can state where the forecast was wrong and what they changed as a result.
A12: C5 | B12: Cash, treasury and working capital | C12: Preferred | D12: 8 | E12: No ownership of a cash position or a payment cycle. | F12: Has owned a cash forecast and a payment run, and understands the entity's working-capital cycle. | G12: Has managed a genuine liquidity constraint - covenant, facility, or collection crisis - and can describe the trade-offs they made.
A13: C6 | B13: Systems, data and reporting tooling | C13: Must | D13: 10 | E13: Works only inside a single ERP screen; spreadsheets are manual and unstructured. | F13: Is fluent in the entity's ERP class and can build the reporting that sits on top of it without help. | G13: Has led or materially supported an implementation, migration, or reporting rebuild, and can describe what broke and how they handled it.
A14: C7 | B14: Team leadership and delegation | C14: Preferred | D14: 10 | E14: Individual contributor only; no evidence of supervising or reviewing others' work. | F14: Has supervised a team of comparable size, including review of their work and management of the close timetable across them. | G14: Has hired, developed, or performance-managed finance staff, and can describe a specific person whose capability they measurably changed.
A15: C8 | B15: Stakeholder communication and reporting | C15: Must | D15: 10 | E15: Communicates in ledger terms; cannot explain a number to a non-finance audience. | F15: Presents regularly to management or the board and can translate a variance into a business cause without prompting. | G15: Has held a position under real challenge - from a board, an auditor, a lender, or a regulator - and can describe how they evidenced it.
A16: C9 | B16: Jurisdictional and regulatory exposure | C16: Preferred | D16: 8 | E16: No exposure to the entity's tax or regulatory regime. | F16: Has operated under the entity's regime (e.g. UAE corporate tax, VAT, ZATCA, free-zone rules) and knows the filing calendar that applies. | G16: Has taken the entity or a comparable one through a first filing, an assessment, or a regime change, and can describe the position taken.
B17: Total | D17: =SUM(D8:D16) -> 100
B18: Criteria in use | D18: =COUNTA(B8:B16) -> 9
B19: Lock check | C19: =IF(D18<4,"Not lockable: fewer than 4 criteria",IF(D18>9,"Not lockable: more than 9 criteria",IF(SUMPRODUCT((B8:B16<>"")*(D8:D16=""))>0,"Not lockable: a named criterion has no weight",IF(SUMPRODUCT((B8:B16="")*(D8:D16<>""))>0,"Not lockable: a weight has no criterion",IF(D17<>100,"Not lockable: weights total "&D17&", not 100","Ready to lock"))))) -> Ready to lock
B21: Source | C21: Default finance rubric and anchors from the Calibre kit v1.0 working file. No criterion may touch personality, health or a protected characteristic.

Sheet 02 Scores
A1: CALIBRE BY DAFTAR
A2: 02 · Scores before calibration
A3: One row per finalist and criterion. Enter each panelist's score, evidence basis and note after all have submitted. Never edit a score once entered.
A5: Scores entered | C5: =IF('00 Setup'!C13*'00 Setup'!C22=0,"Name the panel and finalists on 00 Setup",COUNT(F7:J60)&" of "&('00 Setup'!C13*'00 Setup'!C22*'01 Rubric'!D18)) -> Name the panel and finalists on 00 Setup | E5: =IF(COUNT(F7:J60)=0,"",IF(COUNT(F7:J60)>='00 Setup'!C13*'00 Setup'!C22*'01 Rubric'!D18,"All in: ready to reveal","Waiting for scores"))
A6: Finalist | B6: Ref | C6: Criterion | D6: Weight | E6: P1 score | F6: P2 score | G6: P3 score | H6: P4 score | I6: P5 score | J6: P1 evidence basis | K6: P2 evidence basis | L6: P3 evidence basis | M6: P4 evidence basis | N6: P5 evidence basis | O6: P1 evidence note | P6: P2 evidence note | Q6: P3 evidence note | R6: P4 evidence note | S6: P5 evidence note
A7: ="K1"&IF('00 Setup'!B16="",""," · "&'00 Setup'!B16) -> K1 | B7: C1 | C7: =IF('01 Rubric'!B8="","",'01 Rubric'!B8) -> Technical accounting and IFRS application | D7: =IF('01 Rubric'!D8="","",'01 Rubric'!D8) -> 15
A8: ="K1"&IF('00 Setup'!B16="",""," · "&'00 Setup'!B16) -> K1 | B8: C2 | C8: =IF('01 Rubric'!B9="","",'01 Rubric'!B9) -> Financial reporting and close ownership | D8: =IF('01 Rubric'!D9="","",'01 Rubric'!D9) -> 15
A9: ="K1"&IF('00 Setup'!B16="",""," · "&'00 Setup'!B16) -> K1 | B9: C3 | C9: =IF('01 Rubric'!B10="","",'01 Rubric'!B10) -> Controls, compliance and audit readiness | D9: =IF('01 Rubric'!D10="","",'01 Rubric'!D10) -> 12
A10: ="K1"&IF('00 Setup'!B16="",""," · "&'00 Setup'!B16) -> K1 | B10: C4 | C10: =IF('01 Rubric'!B11="","",'01 Rubric'!B11) -> Planning, budgeting and forecasting | D10: =IF('01 Rubric'!D11="","",'01 Rubric'!D11) -> 12
A11: ="K1"&IF('00 Setup'!B16="",""," · "&'00 Setup'!B16) -> K1 | B11: C5 | C11: =IF('01 Rubric'!B12="","",'01 Rubric'!B12) -> Cash, treasury and working capital | D11: =IF('01 Rubric'!D12="","",'01 Rubric'!D12) -> 8
A12: ="K1"&IF('00 Setup'!B16="",""," · "&'00 Setup'!B16) -> K1 | B12: C6 | C12: =IF('01 Rubric'!B13="","",'01 Rubric'!B13) -> Systems, data and reporting tooling | D12: =IF('01 Rubric'!D13="","",'01 Rubric'!D13) -> 10
A13: ="K1"&IF('00 Setup'!B16="",""," · "&'00 Setup'!B16) -> K1 | B13: C7 | C13: =IF('01 Rubric'!B14="","",'01 Rubric'!B14) -> Team leadership and delegation | D13: =IF('01 Rubric'!D14="","",'01 Rubric'!D14) -> 10
A14: ="K1"&IF('00 Setup'!B16="",""," · "&'00 Setup'!B16) -> K1 | B14: C8 | C14: =IF('01 Rubric'!B15="","",'01 Rubric'!B15) -> Stakeholder communication and reporting | D14: =IF('01 Rubric'!D15="","",'01 Rubric'!D15) -> 10
A15: ="K1"&IF('00 Setup'!B16="",""," · "&'00 Setup'!B16) -> K1 | B15: C9 | C15: =IF('01 Rubric'!B16="","",'01 Rubric'!B16) -> Jurisdictional and regulatory exposure | D15: =IF('01 Rubric'!D16="","",'01 Rubric'!D16) -> 8
A16: ="K2"&IF('00 Setup'!B17="",""," · "&'00 Setup'!B17) -> K2 | B16: C1 | C16: =IF('01 Rubric'!B8="","",'01 Rubric'!B8) -> Technical accounting and IFRS application | D16: =IF('01 Rubric'!D8="","",'01 Rubric'!D8) -> 15
A17: ="K2"&IF('00 Setup'!B17="",""," · "&'00 Setup'!B17) -> K2 | B17: C2 | C17: =IF('01 Rubric'!B9="","",'01 Rubric'!B9) -> Financial reporting and close ownership | D17: =IF('01 Rubric'!D9="","",'01 Rubric'!D9) -> 15
A18: ="K2"&IF('00 Setup'!B17="",""," · "&'00 Setup'!B17) -> K2 | B18: C3 | C18: =IF('01 Rubric'!B10="","",'01 Rubric'!B10) -> Controls, compliance and audit readiness | D18: =IF('01 Rubric'!D10="","",'01 Rubric'!D10) -> 12
A19: ="K2"&IF('00 Setup'!B17="",""," · "&'00 Setup'!B17) -> K2 | B19: C4 | C19: =IF('01 Rubric'!B11="","",'01 Rubric'!B11) -> Planning, budgeting and forecasting | D19: =IF('01 Rubric'!D11="","",'01 Rubric'!D11) -> 12
A20: ="K2"&IF('00 Setup'!B17="",""," · "&'00 Setup'!B17) -> K2 | B20: C5 | C20: =IF('01 Rubric'!B12="","",'01 Rubric'!B12) -> Cash, treasury and working capital | D20: =IF('01 Rubric'!D12="","",'01 Rubric'!D12) -> 8
A21: ="K2"&IF('00 Setup'!B17="",""," · "&'00 Setup'!B17) -> K2 | B21: C6 | C21: =IF('01 Rubric'!B13="","",'01 Rubric'!B13) -> Systems, data and reporting tooling | D21: =IF('01 Rubric'!D13="","",'01 Rubric'!D13) -> 10
A22: ="K2"&IF('00 Setup'!B17="",""," · "&'00 Setup'!B17) -> K2 | B22: C7 | C22: =IF('01 Rubric'!B14="","",'01 Rubric'!B14) -> Team leadership and delegation | D22: =IF('01 Rubric'!D14="","",'01 Rubric'!D14) -> 10
A23: ="K2"&IF('00 Setup'!B17="",""," · "&'00 Setup'!B17) -> K2 | B23: C8 | C23: =IF('01 Rubric'!B15="","",'01 Rubric'!B15) -> Stakeholder communication and reporting | D23: =IF('01 Rubric'!D15="","",'01 Rubric'!D15) -> 10
A24: ="K2"&IF('00 Setup'!B17="",""," · "&'00 Setup'!B17) -> K2 | B24: C9 | C24: =IF('01 Rubric'!B16="","",'01 Rubric'!B16) -> Jurisdictional and regulatory exposure | D24: =IF('01 Rubric'!D16="","",'01 Rubric'!D16) -> 8
A25: ="K3"&IF('00 Setup'!B18="",""," · "&'00 Setup'!B18) -> K3 | B25: C1 | C25: =IF('01 Rubric'!B8="","",'01 Rubric'!B8) -> Technical accounting and IFRS application | D25: =IF('01 Rubric'!D8="","",'01 Rubric'!D8) -> 15
A26: ="K3"&IF('00 Setup'!B18="",""," · "&'00 Setup'!B18) -> K3 | B26: C2 | C26: =IF('01 Rubric'!B9="","",'01 Rubric'!B9) -> Financial reporting and close ownership | D26: =IF('01 Rubric'!D9="","",'01 Rubric'!D9) -> 15
A27: ="K3"&IF('00 Setup'!B18="",""," · "&'00 Setup'!B18) -> K3 | B27: C3 | C27: =IF('01 Rubric'!B10="","",'01 Rubric'!B10) -> Controls, compliance and audit readiness | D27: =IF('01 Rubric'!D10="","",'01 Rubric'!D10) -> 12
A28: ="K3"&IF('00 Setup'!B18="",""," · "&'00 Setup'!B18) -> K3 | B28: C4 | C28: =IF('01 Rubric'!B11="","",'01 Rubric'!B11) -> Planning, budgeting and forecasting | D28: =IF('01 Rubric'!D11="","",'01 Rubric'!D11) -> 12
A29: ="K3"&IF('00 Setup'!B18="",""," · "&'00 Setup'!B18) -> K3 | B29: C5 | C29: =IF('01 Rubric'!B12="","",'01 Rubric'!B12) -> Cash, treasury and working capital | D29: =IF('01 Rubric'!D12="","",'01 Rubric'!D12) -> 8
A30: ="K3"&IF('00 Setup'!B18="",""," · "&'00 Setup'!B18) -> K3 | B30: C6 | C30: =IF('01 Rubric'!B13="","",'01 Rubric'!B13) -> Systems, data and reporting tooling | D30: =IF('01 Rubric'!D13="","",'01 Rubric'!D13) -> 10
A31: ="K3"&IF('00 Setup'!B18="",""," · "&'00 Setup'!B18) -> K3 | B31: C7 | C31: =IF('01 Rubric'!B14="","",'01 Rubric'!B14) -> Team leadership and delegation | D31: =IF('01 Rubric'!D14="","",'01 Rubric'!D14) -> 10
A32: ="K3"&IF('00 Setup'!B18="",""," · "&'00 Setup'!B18) -> K3 | B32: C8 | C32: =IF('01 Rubric'!B15="","",'01 Rubric'!B15) -> Stakeholder communication and reporting | D32: =IF('01 Rubric'!D15="","",'01 Rubric'!D15) -> 10
A33: ="K3"&IF('00 Setup'!B18="",""," · "&'00 Setup'!B18) -> K3 | B33: C9 | C33: =IF('01 Rubric'!B16="","",'01 Rubric'!B16) -> Jurisdictional and regulatory exposure | D33: =IF('01 Rubric'!D16="","",'01 Rubric'!D16) -> 8
A34: ="K4"&IF('00 Setup'!B19="",""," · "&'00 Setup'!B19) -> K4 | B34: C1 | C34: =IF('01 Rubric'!B8="","",'01 Rubric'!B8) -> Technical accounting and IFRS application | D34: =IF('01 Rubric'!D8="","",'01 Rubric'!D8) -> 15
A35: ="K4"&IF('00 Setup'!B19="",""," · "&'00 Setup'!B19) -> K4 | B35: C2 | C35: =IF('01 Rubric'!B9="","",'01 Rubric'!B9) -> Financial reporting and close ownership | D35: =IF('01 Rubric'!D9="","",'01 Rubric'!D9) -> 15
A36: ="K4"&IF('00 Setup'!B19="",""," · "&'00 Setup'!B19) -> K4 | B36: C3 | C36: =IF('01 Rubric'!B10="","",'01 Rubric'!B10) -> Controls, compliance and audit readiness | D36: =IF('01 Rubric'!D10="","",'01 Rubric'!D10) -> 12
A37: ="K4"&IF('00 Setup'!B19="",""," · "&'00 Setup'!B19) -> K4 | B37: C4 | C37: =IF('01 Rubric'!B11="","",'01 Rubric'!B11) -> Planning, budgeting and forecasting | D37: =IF('01 Rubric'!D11="","",'01 Rubric'!D11) -> 12
A38: ="K4"&IF('00 Setup'!B19="",""," · "&'00 Setup'!B19) -> K4 | B38: C5 | C38: =IF('01 Rubric'!B12="","",'01 Rubric'!B12) -> Cash, treasury and working capital | D38: =IF('01 Rubric'!D12="","",'01 Rubric'!D12) -> 8
A39: ="K4"&IF('00 Setup'!B19="",""," · "&'00 Setup'!B19) -> K4 | B39: C6 | C39: =IF('01 Rubric'!B13="","",'01 Rubric'!B13) -> Systems, data and reporting tooling | D39: =IF('01 Rubric'!D13="","",'01 Rubric'!D13) -> 10
A40: ="K4"&IF('00 Setup'!B19="",""," · "&'00 Setup'!B19) -> K4 | B40: C7 | C40: =IF('01 Rubric'!B14="","",'01 Rubric'!B14) -> Team leadership and delegation | D40: =IF('01 Rubric'!D14="","",'01 Rubric'!D14) -> 10
A41: ="K4"&IF('00 Setup'!B19="",""," · "&'00 Setup'!B19) -> K4 | B41: C8 | C41: =IF('01 Rubric'!B15="","",'01 Rubric'!B15) -> Stakeholder communication and reporting | D41: =IF('01 Rubric'!D15="","",'01 Rubric'!D15) -> 10
A42: ="K4"&IF('00 Setup'!B19="",""," · "&'00 Setup'!B19) -> K4 | B42: C9 | C42: =IF('01 Rubric'!B16="","",'01 Rubric'!B16) -> Jurisdictional and regulatory exposure | D42: =IF('01 Rubric'!D16="","",'01 Rubric'!D16) -> 8
A43: ="K5"&IF('00 Setup'!B20="",""," · "&'00 Setup'!B20) -> K5 | B43: C1 | C43: =IF('01 Rubric'!B8="","",'01 Rubric'!B8) -> Technical accounting and IFRS application | D43: =IF('01 Rubric'!D8="","",'01 Rubric'!D8) -> 15
A44: ="K5"&IF('00 Setup'!B20="",""," · "&'00 Setup'!B20) -> K5 | B44: C2 | C44: =IF('01 Rubric'!B9="","",'01 Rubric'!B9) -> Financial reporting and close ownership | D44: =IF('01 Rubric'!D9="","",'01 Rubric'!D9) -> 15
A45: ="K5"&IF('00 Setup'!B20="",""," · "&'00 Setup'!B20) -> K5 | B45: C3 | C45: =IF('01 Rubric'!B10="","",'01 Rubric'!B10) -> Controls, compliance and audit readiness | D45: =IF('01 Rubric'!D10="","",'01 Rubric'!D10) -> 12
A46: ="K5"&IF('00 Setup'!B20="",""," · "&'00 Setup'!B20) -> K5 | B46: C4 | C46: =IF('01 Rubric'!B11="","",'01 Rubric'!B11) -> Planning, budgeting and forecasting | D46: =IF('01 Rubric'!D11="","",'01 Rubric'!D11) -> 12
A47: ="K5"&IF('00 Setup'!B20="",""," · "&'00 Setup'!B20) -> K5 | B47: C5 | C47: =IF('01 Rubric'!B12="","",'01 Rubric'!B12) -> Cash, treasury and working capital | D47: =IF('01 Rubric'!D12="","",'01 Rubric'!D12) -> 8
A48: ="K5"&IF('00 Setup'!B20="",""," · "&'00 Setup'!B20) -> K5 | B48: C6 | C48: =IF('01 Rubric'!B13="","",'01 Rubric'!B13) -> Systems, data and reporting tooling | D48: =IF('01 Rubric'!D13="","",'01 Rubric'!D13) -> 10
A49: ="K5"&IF('00 Setup'!B20="",""," · "&'00 Setup'!B20) -> K5 | B49: C7 | C49: =IF('01 Rubric'!B14="","",'01 Rubric'!B14) -> Team leadership and delegation | D49: =IF('01 Rubric'!D14="","",'01 Rubric'!D14) -> 10
A50: ="K5"&IF('00 Setup'!B20="",""," · "&'00 Setup'!B20) -> K5 | B50: C8 | C50: =IF('01 Rubric'!B15="","",'01 Rubric'!B15) -> Stakeholder communication and reporting | D50: =IF('01 Rubric'!D15="","",'01 Rubric'!D15) -> 10
A51: ="K5"&IF('00 Setup'!B20="",""," · "&'00 Setup'!B20) -> K5 | B51: C9 | C51: =IF('01 Rubric'!B16="","",'01 Rubric'!B16) -> Jurisdictional and regulatory exposure | D51: =IF('01 Rubric'!D16="","",'01 Rubric'!D16) -> 8
A52: ="K6"&IF('00 Setup'!B21="",""," · "&'00 Setup'!B21) -> K6 | B52: C1 | C52: =IF('01 Rubric'!B8="","",'01 Rubric'!B8) -> Technical accounting and IFRS application | D52: =IF('01 Rubric'!D8="","",'01 Rubric'!D8) -> 15
A53: ="K6"&IF('00 Setup'!B21="",""," · "&'00 Setup'!B21) -> K6 | B53: C2 | C53: =IF('01 Rubric'!B9="","",'01 Rubric'!B9) -> Financial reporting and close ownership | D53: =IF('01 Rubric'!D9="","",'01 Rubric'!D9) -> 15
A54: ="K6"&IF('00 Setup'!B21="",""," · "&'00 Setup'!B21) -> K6 | B54: C3 | C54: =IF('01 Rubric'!B10="","",'01 Rubric'!B10) -> Controls, compliance and audit readiness | D54: =IF('01 Rubric'!D10="","",'01 Rubric'!D10) -> 12
A55: ="K6"&IF('00 Setup'!B21="",""," · "&'00 Setup'!B21) -> K6 | B55: C4 | C55: =IF('01 Rubric'!B11="","",'01 Rubric'!B11) -> Planning, budgeting and forecasting | D55: =IF('01 Rubric'!D11="","",'01 Rubric'!D11) -> 12
A56: ="K6"&IF('00 Setup'!B21="",""," · "&'00 Setup'!B21) -> K6 | B56: C5 | C56: =IF('01 Rubric'!B12="","",'01 Rubric'!B12) -> Cash, treasury and working capital | D56: =IF('01 Rubric'!D12="","",'01 Rubric'!D12) -> 8
A57: ="K6"&IF('00 Setup'!B21="",""," · "&'00 Setup'!B21) -> K6 | B57: C6 | C57: =IF('01 Rubric'!B13="","",'01 Rubric'!B13) -> Systems, data and reporting tooling | D57: =IF('01 Rubric'!D13="","",'01 Rubric'!D13) -> 10
A58: ="K6"&IF('00 Setup'!B21="",""," · "&'00 Setup'!B21) -> K6 | B58: C7 | C58: =IF('01 Rubric'!B14="","",'01 Rubric'!B14) -> Team leadership and delegation | D58: =IF('01 Rubric'!D14="","",'01 Rubric'!D14) -> 10
A59: ="K6"&IF('00 Setup'!B21="",""," · "&'00 Setup'!B21) -> K6 | B59: C8 | C59: =IF('01 Rubric'!B15="","",'01 Rubric'!B15) -> Stakeholder communication and reporting | D59: =IF('01 Rubric'!D15="","",'01 Rubric'!D15) -> 10
A60: ="K6"&IF('00 Setup'!B21="",""," · "&'00 Setup'!B21) -> K6 | B60: C9 | C60: =IF('01 Rubric'!B16="","",'01 Rubric'!B16) -> Jurisdictional and regulatory exposure | D60: =IF('01 Rubric'!D16="","",'01 Rubric'!D16) -> 8

Sheet 03 Divergence
A1: CALIBRE BY DAFTAR
A2: 03 · Where the panel diverged
A3: Calculated from sheet 02. Scores of 0 mean no evidence and are left out of the spread and the mean. No totals appear before calibration.
A6: Finalist | B6: Ref | C6: Criterion | D6: Scores entered | E6: Scoring > 0 | F6: Min | G6: Max | H6: Spread | I6: Mean | J6: Provisional | K6: Flag
A7: ="K1"&IF('00 Setup'!B16="",""," · "&'00 Setup'!B16) -> K1 | B7: C1 | C7: =IF('01 Rubric'!B8="","",'01 Rubric'!B8) -> Technical accounting and IFRS application | D7: =COUNT('02 Scores'!F7:J7) -> 0 | E7: =COUNTIF('02 Scores'!F7:J7,">0") -> 0 | F7: =IF(E7=0,"",SMALL('02 Scores'!F7:J7,COUNTIF('02 Scores'!F7:J7,0)+1)) | G7: =IF(E7=0,"",MAX('02 Scores'!F7:J7)) | H7: =IF(E7=0,"",G7-F7) | I7: =IF(E7=0,"",AVERAGEIF('02 Scores'!F7:J7,">0")) | J7: =IF(E7=0,"",ROUNDUP(I7-0.5,0)) | K7: =IF(OR(C7="",D7=0),"",IF(E7=0,"No evidence",IF(H7>=3,"Contradiction",IF(H7=2,"Divergence","Agreement"))))
A8: ="K1"&IF('00 Setup'!B16="",""," · "&'00 Setup'!B16) -> K1 | B8: C2 | C8: =IF('01 Rubric'!B9="","",'01 Rubric'!B9) -> Financial reporting and close ownership | D8: =COUNT('02 Scores'!F8:J8) -> 0 | E8: =COUNTIF('02 Scores'!F8:J8,">0") -> 0 | F8: =IF(E8=0,"",SMALL('02 Scores'!F8:J8,COUNTIF('02 Scores'!F8:J8,0)+1)) | G8: =IF(E8=0,"",MAX('02 Scores'!F8:J8)) | H8: =IF(E8=0,"",G8-F8) | I8: =IF(E8=0,"",AVERAGEIF('02 Scores'!F8:J8,">0")) | J8: =IF(E8=0,"",ROUNDUP(I8-0.5,0)) | K8: =IF(OR(C8="",D8=0),"",IF(E8=0,"No evidence",IF(H8>=3,"Contradiction",IF(H8=2,"Divergence","Agreement"))))
A9: ="K1"&IF('00 Setup'!B16="",""," · "&'00 Setup'!B16) -> K1 | B9: C3 | C9: =IF('01 Rubric'!B10="","",'01 Rubric'!B10) -> Controls, compliance and audit readiness | D9: =COUNT('02 Scores'!F9:J9) -> 0 | E9: =COUNTIF('02 Scores'!F9:J9,">0") -> 0 | F9: =IF(E9=0,"",SMALL('02 Scores'!F9:J9,COUNTIF('02 Scores'!F9:J9,0)+1)) | G9: =IF(E9=0,"",MAX('02 Scores'!F9:J9)) | H9: =IF(E9=0,"",G9-F9) | I9: =IF(E9=0,"",AVERAGEIF('02 Scores'!F9:J9,">0")) | J9: =IF(E9=0,"",ROUNDUP(I9-0.5,0)) | K9: =IF(OR(C9="",D9=0),"",IF(E9=0,"No evidence",IF(H9>=3,"Contradiction",IF(H9=2,"Divergence","Agreement"))))
A10: ="K1"&IF('00 Setup'!B16="",""," · "&'00 Setup'!B16) -> K1 | B10: C4 | C10: =IF('01 Rubric'!B11="","",'01 Rubric'!B11) -> Planning, budgeting and forecasting | D10: =COUNT('02 Scores'!F10:J10) -> 0 | E10: =COUNTIF('02 Scores'!F10:J10,">0") -> 0 | F10: =IF(E10=0,"",SMALL('02 Scores'!F10:J10,COUNTIF('02 Scores'!F10:J10,0)+1)) | G10: =IF(E10=0,"",MAX('02 Scores'!F10:J10)) | H10: =IF(E10=0,"",G10-F10) | I10: =IF(E10=0,"",AVERAGEIF('02 Scores'!F10:J10,">0")) | J10: =IF(E10=0,"",ROUNDUP(I10-0.5,0)) | K10: =IF(OR(C10="",D10=0),"",IF(E10=0,"No evidence",IF(H10>=3,"Contradiction",IF(H10=2,"Divergence","Agreement"))))
A11: ="K1"&IF('00 Setup'!B16="",""," · "&'00 Setup'!B16) -> K1 | B11: C5 | C11: =IF('01 Rubric'!B12="","",'01 Rubric'!B12) -> Cash, treasury and working capital | D11: =COUNT('02 Scores'!F11:J11) -> 0 | E11: =COUNTIF('02 Scores'!F11:J11,">0") -> 0 | F11: =IF(E11=0,"",SMALL('02 Scores'!F11:J11,COUNTIF('02 Scores'!F11:J11,0)+1)) | G11: =IF(E11=0,"",MAX('02 Scores'!F11:J11)) | H11: =IF(E11=0,"",G11-F11) | I11: =IF(E11=0,"",AVERAGEIF('02 Scores'!F11:J11,">0")) | J11: =IF(E11=0,"",ROUNDUP(I11-0.5,0)) | K11: =IF(OR(C11="",D11=0),"",IF(E11=0,"No evidence",IF(H11>=3,"Contradiction",IF(H11=2,"Divergence","Agreement"))))
A12: ="K1"&IF('00 Setup'!B16="",""," · "&'00 Setup'!B16) -> K1 | B12: C6 | C12: =IF('01 Rubric'!B13="","",'01 Rubric'!B13) -> Systems, data and reporting tooling | D12: =COUNT('02 Scores'!F12:J12) -> 0 | E12: =COUNTIF('02 Scores'!F12:J12,">0") -> 0 | F12: =IF(E12=0,"",SMALL('02 Scores'!F12:J12,COUNTIF('02 Scores'!F12:J12,0)+1)) | G12: =IF(E12=0,"",MAX('02 Scores'!F12:J12)) | H12: =IF(E12=0,"",G12-F12) | I12: =IF(E12=0,"",AVERAGEIF('02 Scores'!F12:J12,">0")) | J12: =IF(E12=0,"",ROUNDUP(I12-0.5,0)) | K12: =IF(OR(C12="",D12=0),"",IF(E12=0,"No evidence",IF(H12>=3,"Contradiction",IF(H12=2,"Divergence","Agreement"))))
A13: ="K1"&IF('00 Setup'!B16="",""," · "&'00 Setup'!B16) -> K1 | B13: C7 | C13: =IF('01 Rubric'!B14="","",'01 Rubric'!B14) -> Team leadership and delegation | D13: =COUNT('02 Scores'!F13:J13) -> 0 | E13: =COUNTIF('02 Scores'!F13:J13,">0") -> 0 | F13: =IF(E13=0,"",SMALL('02 Scores'!F13:J13,COUNTIF('02 Scores'!F13:J13,0)+1)) | G13: =IF(E13=0,"",MAX('02 Scores'!F13:J13)) | H13: =IF(E13=0,"",G13-F13) | I13: =IF(E13=0,"",AVERAGEIF('02 Scores'!F13:J13,">0")) | J13: =IF(E13=0,"",ROUNDUP(I13-0.5,0)) | K13: =IF(OR(C13="",D13=0),"",IF(E13=0,"No evidence",IF(H13>=3,"Contradiction",IF(H13=2,"Divergence","Agreement"))))
A14: ="K1"&IF('00 Setup'!B16="",""," · "&'00 Setup'!B16) -> K1 | B14: C8 | C14: =IF('01 Rubric'!B15="","",'01 Rubric'!B15) -> Stakeholder communication and reporting | D14: =COUNT('02 Scores'!F14:J14) -> 0 | E14: =COUNTIF('02 Scores'!F14:J14,">0") -> 0 | F14: =IF(E14=0,"",SMALL('02 Scores'!F14:J14,COUNTIF('02 Scores'!F14:J14,0)+1)) | G14: =IF(E14=0,"",MAX('02 Scores'!F14:J14)) | H14: =IF(E14=0,"",G14-F14) | I14: =IF(E14=0,"",AVERAGEIF('02 Scores'!F14:J14,">0")) | J14: =IF(E14=0,"",ROUNDUP(I14-0.5,0)) | K14: =IF(OR(C14="",D14=0),"",IF(E14=0,"No evidence",IF(H14>=3,"Contradiction",IF(H14=2,"Divergence","Agreement"))))
A15: ="K1"&IF('00 Setup'!B16="",""," · "&'00 Setup'!B16) -> K1 | B15: C9 | C15: =IF('01 Rubric'!B16="","",'01 Rubric'!B16) -> Jurisdictional and regulatory exposure | D15: =COUNT('02 Scores'!F15:J15) -> 0 | E15: =COUNTIF('02 Scores'!F15:J15,">0") -> 0 | F15: =IF(E15=0,"",SMALL('02 Scores'!F15:J15,COUNTIF('02 Scores'!F15:J15,0)+1)) | G15: =IF(E15=0,"",MAX('02 Scores'!F15:J15)) | H15: =IF(E15=0,"",G15-F15) | I15: =IF(E15=0,"",AVERAGEIF('02 Scores'!F15:J15,">0")) | J15: =IF(E15=0,"",ROUNDUP(I15-0.5,0)) | K15: =IF(OR(C15="",D15=0),"",IF(E15=0,"No evidence",IF(H15>=3,"Contradiction",IF(H15=2,"Divergence","Agreement"))))
A16: ="K2"&IF('00 Setup'!B17="",""," · "&'00 Setup'!B17) -> K2 | B16: C1 | C16: =IF('01 Rubric'!B8="","",'01 Rubric'!B8) -> Technical accounting and IFRS application | D16: =COUNT('02 Scores'!F16:J16) -> 0 | E16: =COUNTIF('02 Scores'!F16:J16,">0") -> 0 | F16: =IF(E16=0,"",SMALL('02 Scores'!F16:J16,COUNTIF('02 Scores'!F16:J16,0)+1)) | G16: =IF(E16=0,"",MAX('02 Scores'!F16:J16)) | H16: =IF(E16=0,"",G16-F16) | I16: =IF(E16=0,"",AVERAGEIF('02 Scores'!F16:J16,">0")) | J16: =IF(E16=0,"",ROUNDUP(I16-0.5,0)) | K16: =IF(OR(C16="",D16=0),"",IF(E16=0,"No evidence",IF(H16>=3,"Contradiction",IF(H16=2,"Divergence","Agreement"))))
A17: ="K2"&IF('00 Setup'!B17="",""," · "&'00 Setup'!B17) -> K2 | B17: C2 | C17: =IF('01 Rubric'!B9="","",'01 Rubric'!B9) -> Financial reporting and close ownership | D17: =COUNT('02 Scores'!F17:J17) -> 0 | E17: =COUNTIF('02 Scores'!F17:J17,">0") -> 0 | F17: =IF(E17=0,"",SMALL('02 Scores'!F17:J17,COUNTIF('02 Scores'!F17:J17,0)+1)) | G17: =IF(E17=0,"",MAX('02 Scores'!F17:J17)) | H17: =IF(E17=0,"",G17-F17) | I17: =IF(E17=0,"",AVERAGEIF('02 Scores'!F17:J17,">0")) | J17: =IF(E17=0,"",ROUNDUP(I17-0.5,0)) | K17: =IF(OR(C17="",D17=0),"",IF(E17=0,"No evidence",IF(H17>=3,"Contradiction",IF(H17=2,"Divergence","Agreement"))))
A18: ="K2"&IF('00 Setup'!B17="",""," · "&'00 Setup'!B17) -> K2 | B18: C3 | C18: =IF('01 Rubric'!B10="","",'01 Rubric'!B10) -> Controls, compliance and audit readiness | D18: =COUNT('02 Scores'!F18:J18) -> 0 | E18: =COUNTIF('02 Scores'!F18:J18,">0") -> 0 | F18: =IF(E18=0,"",SMALL('02 Scores'!F18:J18,COUNTIF('02 Scores'!F18:J18,0)+1)) | G18: =IF(E18=0,"",MAX('02 Scores'!F18:J18)) | H18: =IF(E18=0,"",G18-F18) | I18: =IF(E18=0,"",AVERAGEIF('02 Scores'!F18:J18,">0")) | J18: =IF(E18=0,"",ROUNDUP(I18-0.5,0)) | K18: =IF(OR(C18="",D18=0),"",IF(E18=0,"No evidence",IF(H18>=3,"Contradiction",IF(H18=2,"Divergence","Agreement"))))
A19: ="K2"&IF('00 Setup'!B17="",""," · "&'00 Setup'!B17) -> K2 | B19: C4 | C19: =IF('01 Rubric'!B11="","",'01 Rubric'!B11) -> Planning, budgeting and forecasting | D19: =COUNT('02 Scores'!F19:J19) -> 0 | E19: =COUNTIF('02 Scores'!F19:J19,">0") -> 0 | F19: =IF(E19=0,"",SMALL('02 Scores'!F19:J19,COUNTIF('02 Scores'!F19:J19,0)+1)) | G19: =IF(E19=0,"",MAX('02 Scores'!F19:J19)) | H19: =IF(E19=0,"",G19-F19) | I19: =IF(E19=0,"",AVERAGEIF('02 Scores'!F19:J19,">0")) | J19: =IF(E19=0,"",ROUNDUP(I19-0.5,0)) | K19: =IF(OR(C19="",D19=0),"",IF(E19=0,"No evidence",IF(H19>=3,"Contradiction",IF(H19=2,"Divergence","Agreement"))))
A20: ="K2"&IF('00 Setup'!B17="",""," · "&'00 Setup'!B17) -> K2 | B20: C5 | C20: =IF('01 Rubric'!B12="","",'01 Rubric'!B12) -> Cash, treasury and working capital | D20: =COUNT('02 Scores'!F20:J20) -> 0 | E20: =COUNTIF('02 Scores'!F20:J20,">0") -> 0 | F20: =IF(E20=0,"",SMALL('02 Scores'!F20:J20,COUNTIF('02 Scores'!F20:J20,0)+1)) | G20: =IF(E20=0,"",MAX('02 Scores'!F20:J20)) | H20: =IF(E20=0,"",G20-F20) | I20: =IF(E20=0,"",AVERAGEIF('02 Scores'!F20:J20,">0")) | J20: =IF(E20=0,"",ROUNDUP(I20-0.5,0)) | K20: =IF(OR(C20="",D20=0),"",IF(E20=0,"No evidence",IF(H20>=3,"Contradiction",IF(H20=2,"Divergence","Agreement"))))
A21: ="K2"&IF('00 Setup'!B17="",""," · "&'00 Setup'!B17) -> K2 | B21: C6 | C21: =IF('01 Rubric'!B13="","",'01 Rubric'!B13) -> Systems, data and reporting tooling | D21: =COUNT('02 Scores'!F21:J21) -> 0 | E21: =COUNTIF('02 Scores'!F21:J21,">0") -> 0 | F21: =IF(E21=0,"",SMALL('02 Scores'!F21:J21,COUNTIF('02 Scores'!F21:J21,0)+1)) | G21: =IF(E21=0,"",MAX('02 Scores'!F21:J21)) | H21: =IF(E21=0,"",G21-F21) | I21: =IF(E21=0,"",AVERAGEIF('02 Scores'!F21:J21,">0")) | J21: =IF(E21=0,"",ROUNDUP(I21-0.5,0)) | K21: =IF(OR(C21="",D21=0),"",IF(E21=0,"No evidence",IF(H21>=3,"Contradiction",IF(H21=2,"Divergence","Agreement"))))
A22: ="K2"&IF('00 Setup'!B17="",""," · "&'00 Setup'!B17) -> K2 | B22: C7 | C22: =IF('01 Rubric'!B14="","",'01 Rubric'!B14) -> Team leadership and delegation | D22: =COUNT('02 Scores'!F22:J22) -> 0 | E22: =COUNTIF('02 Scores'!F22:J22,">0") -> 0 | F22: =IF(E22=0,"",SMALL('02 Scores'!F22:J22,COUNTIF('02 Scores'!F22:J22,0)+1)) | G22: =IF(E22=0,"",MAX('02 Scores'!F22:J22)) | H22: =IF(E22=0,"",G22-F22) | I22: =IF(E22=0,"",AVERAGEIF('02 Scores'!F22:J22,">0")) | J22: =IF(E22=0,"",ROUNDUP(I22-0.5,0)) | K22: =IF(OR(C22="",D22=0),"",IF(E22=0,"No evidence",IF(H22>=3,"Contradiction",IF(H22=2,"Divergence","Agreement"))))
A23: ="K2"&IF('00 Setup'!B17="",""," · "&'00 Setup'!B17) -> K2 | B23: C8 | C23: =IF('01 Rubric'!B15="","",'01 Rubric'!B15) -> Stakeholder communication and reporting | D23: =COUNT('02 Scores'!F23:J23) -> 0 | E23: =COUNTIF('02 Scores'!F23:J23,">0") -> 0 | F23: =IF(E23=0,"",SMALL('02 Scores'!F23:J23,COUNTIF('02 Scores'!F23:J23,0)+1)) | G23: =IF(E23=0,"",MAX('02 Scores'!F23:J23)) | H23: =IF(E23=0,"",G23-F23) | I23: =IF(E23=0,"",AVERAGEIF('02 Scores'!F23:J23,">0")) | J23: =IF(E23=0,"",ROUNDUP(I23-0.5,0)) | K23: =IF(OR(C23="",D23=0),"",IF(E23=0,"No evidence",IF(H23>=3,"Contradiction",IF(H23=2,"Divergence","Agreement"))))
A24: ="K2"&IF('00 Setup'!B17="",""," · "&'00 Setup'!B17) -> K2 | B24: C9 | C24: =IF('01 Rubric'!B16="","",'01 Rubric'!B16) -> Jurisdictional and regulatory exposure | D24: =COUNT('02 Scores'!F24:J24) -> 0 | E24: =COUNTIF('02 Scores'!F24:J24,">0") -> 0 | F24: =IF(E24=0,"",SMALL('02 Scores'!F24:J24,COUNTIF('02 Scores'!F24:J24,0)+1)) | G24: =IF(E24=0,"",MAX('02 Scores'!F24:J24)) | H24: =IF(E24=0,"",G24-F24) | I24: =IF(E24=0,"",AVERAGEIF('02 Scores'!F24:J24,">0")) | J24: =IF(E24=0,"",ROUNDUP(I24-0.5,0)) | K24: =IF(OR(C24="",D24=0),"",IF(E24=0,"No evidence",IF(H24>=3,"Contradiction",IF(H24=2,"Divergence","Agreement"))))
A25: ="K3"&IF('00 Setup'!B18="",""," · "&'00 Setup'!B18) -> K3 | B25: C1 | C25: =IF('01 Rubric'!B8="","",'01 Rubric'!B8) -> Technical accounting and IFRS application | D25: =COUNT('02 Scores'!F25:J25) -> 0 | E25: =COUNTIF('02 Scores'!F25:J25,">0") -> 0 | F25: =IF(E25=0,"",SMALL('02 Scores'!F25:J25,COUNTIF('02 Scores'!F25:J25,0)+1)) | G25: =IF(E25=0,"",MAX('02 Scores'!F25:J25)) | H25: =IF(E25=0,"",G25-F25) | I25: =IF(E25=0,"",AVERAGEIF('02 Scores'!F25:J25,">0")) | J25: =IF(E25=0,"",ROUNDUP(I25-0.5,0)) | K25: =IF(OR(C25="",D25=0),"",IF(E25=0,"No evidence",IF(H25>=3,"Contradiction",IF(H25=2,"Divergence","Agreement"))))
A26: ="K3"&IF('00 Setup'!B18="",""," · "&'00 Setup'!B18) -> K3 | B26: C2 | C26: =IF('01 Rubric'!B9="","",'01 Rubric'!B9) -> Financial reporting and close ownership | D26: =COUNT('02 Scores'!F26:J26) -> 0 | E26: =COUNTIF('02 Scores'!F26:J26,">0") -> 0 | F26: =IF(E26=0,"",SMALL('02 Scores'!F26:J26,COUNTIF('02 Scores'!F26:J26,0)+1)) | G26: =IF(E26=0,"",MAX('02 Scores'!F26:J26)) | H26: =IF(E26=0,"",G26-F26) | I26: =IF(E26=0,"",AVERAGEIF('02 Scores'!F26:J26,">0")) | J26: =IF(E26=0,"",ROUNDUP(I26-0.5,0)) | K26: =IF(OR(C26="",D26=0),"",IF(E26=0,"No evidence",IF(H26>=3,"Contradiction",IF(H26=2,"Divergence","Agreement"))))
A27: ="K3"&IF('00 Setup'!B18="",""," · "&'00 Setup'!B18) -> K3 | B27: C3 | C27: =IF('01 Rubric'!B10="","",'01 Rubric'!B10) -> Controls, compliance and audit readiness | D27: =COUNT('02 Scores'!F27:J27) -> 0 | E27: =COUNTIF('02 Scores'!F27:J27,">0") -> 0 | F27: =IF(E27=0,"",SMALL('02 Scores'!F27:J27,COUNTIF('02 Scores'!F27:J27,0)+1)) | G27: =IF(E27=0,"",MAX('02 Scores'!F27:J27)) | H27: =IF(E27=0,"",G27-F27) | I27: =IF(E27=0,"",AVERAGEIF('02 Scores'!F27:J27,">0")) | J27: =IF(E27=0,"",ROUNDUP(I27-0.5,0)) | K27: =IF(OR(C27="",D27=0),"",IF(E27=0,"No evidence",IF(H27>=3,"Contradiction",IF(H27=2,"Divergence","Agreement"))))
A28: ="K3"&IF('00 Setup'!B18="",""," · "&'00 Setup'!B18) -> K3 | B28: C4 | C28: =IF('01 Rubric'!B11="","",'01 Rubric'!B11) -> Planning, budgeting and forecasting | D28: =COUNT('02 Scores'!F28:J28) -> 0 | E28: =COUNTIF('02 Scores'!F28:J28,">0") -> 0 | F28: =IF(E28=0,"",SMALL('02 Scores'!F28:J28,COUNTIF('02 Scores'!F28:J28,0)+1)) | G28: =IF(E28=0,"",MAX('02 Scores'!F28:J28)) | H28: =IF(E28=0,"",G28-F28) | I28: =IF(E28=0,"",AVERAGEIF('02 Scores'!F28:J28,">0")) | J28: =IF(E28=0,"",ROUNDUP(I28-0.5,0)) | K28: =IF(OR(C28="",D28=0),"",IF(E28=0,"No evidence",IF(H28>=3,"Contradiction",IF(H28=2,"Divergence","Agreement"))))
A29: ="K3"&IF('00 Setup'!B18="",""," · "&'00 Setup'!B18) -> K3 | B29: C5 | C29: =IF('01 Rubric'!B12="","",'01 Rubric'!B12) -> Cash, treasury and working capital | D29: =COUNT('02 Scores'!F29:J29) -> 0 | E29: =COUNTIF('02 Scores'!F29:J29,">0") -> 0 | F29: =IF(E29=0,"",SMALL('02 Scores'!F29:J29,COUNTIF('02 Scores'!F29:J29,0)+1)) | G29: =IF(E29=0,"",MAX('02 Scores'!F29:J29)) | H29: =IF(E29=0,"",G29-F29) | I29: =IF(E29=0,"",AVERAGEIF('02 Scores'!F29:J29,">0")) | J29: =IF(E29=0,"",ROUNDUP(I29-0.5,0)) | K29: =IF(OR(C29="",D29=0),"",IF(E29=0,"No evidence",IF(H29>=3,"Contradiction",IF(H29=2,"Divergence","Agreement"))))
A30: ="K3"&IF('00 Setup'!B18="",""," · "&'00 Setup'!B18) -> K3 | B30: C6 | C30: =IF('01 Rubric'!B13="","",'01 Rubric'!B13) -> Systems, data and reporting tooling | D30: =COUNT('02 Scores'!F30:J30) -> 0 | E30: =COUNTIF('02 Scores'!F30:J30,">0") -> 0 | F30: =IF(E30=0,"",SMALL('02 Scores'!F30:J30,COUNTIF('02 Scores'!F30:J30,0)+1)) | G30: =IF(E30=0,"",MAX('02 Scores'!F30:J30)) | H30: =IF(E30=0,"",G30-F30) | I30: =IF(E30=0,"",AVERAGEIF('02 Scores'!F30:J30,">0")) | J30: =IF(E30=0,"",ROUNDUP(I30-0.5,0)) | K30: =IF(OR(C30="",D30=0),"",IF(E30=0,"No evidence",IF(H30>=3,"Contradiction",IF(H30=2,"Divergence","Agreement"))))
A31: ="K3"&IF('00 Setup'!B18="",""," · "&'00 Setup'!B18) -> K3 | B31: C7 | C31: =IF('01 Rubric'!B14="","",'01 Rubric'!B14) -> Team leadership and delegation | D31: =COUNT('02 Scores'!F31:J31) -> 0 | E31: =COUNTIF('02 Scores'!F31:J31,">0") -> 0 | F31: =IF(E31=0,"",SMALL('02 Scores'!F31:J31,COUNTIF('02 Scores'!F31:J31,0)+1)) | G31: =IF(E31=0,"",MAX('02 Scores'!F31:J31)) | H31: =IF(E31=0,"",G31-F31) | I31: =IF(E31=0,"",AVERAGEIF('02 Scores'!F31:J31,">0")) | J31: =IF(E31=0,"",ROUNDUP(I31-0.5,0)) | K31: =IF(OR(C31="",D31=0),"",IF(E31=0,"No evidence",IF(H31>=3,"Contradiction",IF(H31=2,"Divergence","Agreement"))))
A32: ="K3"&IF('00 Setup'!B18="",""," · "&'00 Setup'!B18) -> K3 | B32: C8 | C32: =IF('01 Rubric'!B15="","",'01 Rubric'!B15) -> Stakeholder communication and reporting | D32: =COUNT('02 Scores'!F32:J32) -> 0 | E32: =COUNTIF('02 Scores'!F32:J32,">0") -> 0 | F32: =IF(E32=0,"",SMALL('02 Scores'!F32:J32,COUNTIF('02 Scores'!F32:J32,0)+1)) | G32: =IF(E32=0,"",MAX('02 Scores'!F32:J32)) | H32: =IF(E32=0,"",G32-F32) | I32: =IF(E32=0,"",AVERAGEIF('02 Scores'!F32:J32,">0")) | J32: =IF(E32=0,"",ROUNDUP(I32-0.5,0)) | K32: =IF(OR(C32="",D32=0),"",IF(E32=0,"No evidence",IF(H32>=3,"Contradiction",IF(H32=2,"Divergence","Agreement"))))
A33: ="K3"&IF('00 Setup'!B18="",""," · "&'00 Setup'!B18) -> K3 | B33: C9 | C33: =IF('01 Rubric'!B16="","",'01 Rubric'!B16) -> Jurisdictional and regulatory exposure | D33: =COUNT('02 Scores'!F33:J33) -> 0 | E33: =COUNTIF('02 Scores'!F33:J33,">0") -> 0 | F33: =IF(E33=0,"",SMALL('02 Scores'!F33:J33,COUNTIF('02 Scores'!F33:J33,0)+1)) | G33: =IF(E33=0,"",MAX('02 Scores'!F33:J33)) | H33: =IF(E33=0,"",G33-F33) | I33: =IF(E33=0,"",AVERAGEIF('02 Scores'!F33:J33,">0")) | J33: =IF(E33=0,"",ROUNDUP(I33-0.5,0)) | K33: =IF(OR(C33="",D33=0),"",IF(E33=0,"No evidence",IF(H33>=3,"Contradiction",IF(H33=2,"Divergence","Agreement"))))
A34: ="K4"&IF('00 Setup'!B19="",""," · "&'00 Setup'!B19) -> K4 | B34: C1 | C34: =IF('01 Rubric'!B8="","",'01 Rubric'!B8) -> Technical accounting and IFRS application | D34: =COUNT('02 Scores'!F34:J34) -> 0 | E34: =COUNTIF('02 Scores'!F34:J34,">0") -> 0 | F34: =IF(E34=0,"",SMALL('02 Scores'!F34:J34,COUNTIF('02 Scores'!F34:J34,0)+1)) | G34: =IF(E34=0,"",MAX('02 Scores'!F34:J34)) | H34: =IF(E34=0,"",G34-F34) | I34: =IF(E34=0,"",AVERAGEIF('02 Scores'!F34:J34,">0")) | J34: =IF(E34=0,"",ROUNDUP(I34-0.5,0)) | K34: =IF(OR(C34="",D34=0),"",IF(E34=0,"No evidence",IF(H34>=3,"Contradiction",IF(H34=2,"Divergence","Agreement"))))
A35: ="K4"&IF('00 Setup'!B19="",""," · "&'00 Setup'!B19) -> K4 | B35: C2 | C35: =IF('01 Rubric'!B9="","",'01 Rubric'!B9) -> Financial reporting and close ownership | D35: =COUNT('02 Scores'!F35:J35) -> 0 | E35: =COUNTIF('02 Scores'!F35:J35,">0") -> 0 | F35: =IF(E35=0,"",SMALL('02 Scores'!F35:J35,COUNTIF('02 Scores'!F35:J35,0)+1)) | G35: =IF(E35=0,"",MAX('02 Scores'!F35:J35)) | H35: =IF(E35=0,"",G35-F35) | I35: =IF(E35=0,"",AVERAGEIF('02 Scores'!F35:J35,">0")) | J35: =IF(E35=0,"",ROUNDUP(I35-0.5,0)) | K35: =IF(OR(C35="",D35=0),"",IF(E35=0,"No evidence",IF(H35>=3,"Contradiction",IF(H35=2,"Divergence","Agreement"))))
A36: ="K4"&IF('00 Setup'!B19="",""," · "&'00 Setup'!B19) -> K4 | B36: C3 | C36: =IF('01 Rubric'!B10="","",'01 Rubric'!B10) -> Controls, compliance and audit readiness | D36: =COUNT('02 Scores'!F36:J36) -> 0 | E36: =COUNTIF('02 Scores'!F36:J36,">0") -> 0 | F36: =IF(E36=0,"",SMALL('02 Scores'!F36:J36,COUNTIF('02 Scores'!F36:J36,0)+1)) | G36: =IF(E36=0,"",MAX('02 Scores'!F36:J36)) | H36: =IF(E36=0,"",G36-F36) | I36: =IF(E36=0,"",AVERAGEIF('02 Scores'!F36:J36,">0")) | J36: =IF(E36=0,"",ROUNDUP(I36-0.5,0)) | K36: =IF(OR(C36="",D36=0),"",IF(E36=0,"No evidence",IF(H36>=3,"Contradiction",IF(H36=2,"Divergence","Agreement"))))
A37: ="K4"&IF('00 Setup'!B19="",""," · "&'00 Setup'!B19) -> K4 | B37: C4 | C37: =IF('01 Rubric'!B11="","",'01 Rubric'!B11) -> Planning, budgeting and forecasting | D37: =COUNT('02 Scores'!F37:J37) -> 0 | E37: =COUNTIF('02 Scores'!F37:J37,">0") -> 0 | F37: =IF(E37=0,"",SMALL('02 Scores'!F37:J37,COUNTIF('02 Scores'!F37:J37,0)+1)) | G37: =IF(E37=0,"",MAX('02 Scores'!F37:J37)) | H37: =IF(E37=0,"",G37-F37) | I37: =IF(E37=0,"",AVERAGEIF('02 Scores'!F37:J37,">0")) | J37: =IF(E37=0,"",ROUNDUP(I37-0.5,0)) | K37: =IF(OR(C37="",D37=0),"",IF(E37=0,"No evidence",IF(H37>=3,"Contradiction",IF(H37=2,"Divergence","Agreement"))))
A38: ="K4"&IF('00 Setup'!B19="",""," · "&'00 Setup'!B19) -> K4 | B38: C5 | C38: =IF('01 Rubric'!B12="","",'01 Rubric'!B12) -> Cash, treasury and working capital | D38: =COUNT('02 Scores'!F38:J38) -> 0 | E38: =COUNTIF('02 Scores'!F38:J38,">0") -> 0 | F38: =IF(E38=0,"",SMALL('02 Scores'!F38:J38,COUNTIF('02 Scores'!F38:J38,0)+1)) | G38: =IF(E38=0,"",MAX('02 Scores'!F38:J38)) | H38: =IF(E38=0,"",G38-F38) | I38: =IF(E38=0,"",AVERAGEIF('02 Scores'!F38:J38,">0")) | J38: =IF(E38=0,"",ROUNDUP(I38-0.5,0)) | K38: =IF(OR(C38="",D38=0),"",IF(E38=0,"No evidence",IF(H38>=3,"Contradiction",IF(H38=2,"Divergence","Agreement"))))
A39: ="K4"&IF('00 Setup'!B19="",""," · "&'00 Setup'!B19) -> K4 | B39: C6 | C39: =IF('01 Rubric'!B13="","",'01 Rubric'!B13) -> Systems, data and reporting tooling | D39: =COUNT('02 Scores'!F39:J39) -> 0 | E39: =COUNTIF('02 Scores'!F39:J39,">0") -> 0 | F39: =IF(E39=0,"",SMALL('02 Scores'!F39:J39,COUNTIF('02 Scores'!F39:J39,0)+1)) | G39: =IF(E39=0,"",MAX('02 Scores'!F39:J39)) | H39: =IF(E39=0,"",G39-F39) | I39: =IF(E39=0,"",AVERAGEIF('02 Scores'!F39:J39,">0")) | J39: =IF(E39=0,"",ROUNDUP(I39-0.5,0)) | K39: =IF(OR(C39="",D39=0),"",IF(E39=0,"No evidence",IF(H39>=3,"Contradiction",IF(H39=2,"Divergence","Agreement"))))
A40: ="K4"&IF('00 Setup'!B19="",""," · "&'00 Setup'!B19) -> K4 | B40: C7 | C40: =IF('01 Rubric'!B14="","",'01 Rubric'!B14) -> Team leadership and delegation | D40: =COUNT('02 Scores'!F40:J40) -> 0 | E40: =COUNTIF('02 Scores'!F40:J40,">0") -> 0 | F40: =IF(E40=0,"",SMALL('02 Scores'!F40:J40,COUNTIF('02 Scores'!F40:J40,0)+1)) | G40: =IF(E40=0,"",MAX('02 Scores'!F40:J40)) | H40: =IF(E40=0,"",G40-F40) | I40: =IF(E40=0,"",AVERAGEIF('02 Scores'!F40:J40,">0")) | J40: =IF(E40=0,"",ROUNDUP(I40-0.5,0)) | K40: =IF(OR(C40="",D40=0),"",IF(E40=0,"No evidence",IF(H40>=3,"Contradiction",IF(H40=2,"Divergence","Agreement"))))
A41: ="K4"&IF('00 Setup'!B19="",""," · "&'00 Setup'!B19) -> K4 | B41: C8 | C41: =IF('01 Rubric'!B15="","",'01 Rubric'!B15) -> Stakeholder communication and reporting | D41: =COUNT('02 Scores'!F41:J41) -> 0 | E41: =COUNTIF('02 Scores'!F41:J41,">0") -> 0 | F41: =IF(E41=0,"",SMALL('02 Scores'!F41:J41,COUNTIF('02 Scores'!F41:J41,0)+1)) | G41: =IF(E41=0,"",MAX('02 Scores'!F41:J41)) | H41: =IF(E41=0,"",G41-F41) | I41: =IF(E41=0,"",AVERAGEIF('02 Scores'!F41:J41,">0")) | J41: =IF(E41=0,"",ROUNDUP(I41-0.5,0)) | K41: =IF(OR(C41="",D41=0),"",IF(E41=0,"No evidence",IF(H41>=3,"Contradiction",IF(H41=2,"Divergence","Agreement"))))
A42: ="K4"&IF('00 Setup'!B19="",""," · "&'00 Setup'!B19) -> K4 | B42: C9 | C42: =IF('01 Rubric'!B16="","",'01 Rubric'!B16) -> Jurisdictional and regulatory exposure | D42: =COUNT('02 Scores'!F42:J42) -> 0 | E42: =COUNTIF('02 Scores'!F42:J42,">0") -> 0 | F42: =IF(E42=0,"",SMALL('02 Scores'!F42:J42,COUNTIF('02 Scores'!F42:J42,0)+1)) | G42: =IF(E42=0,"",MAX('02 Scores'!F42:J42)) | H42: =IF(E42=0,"",G42-F42) | I42: =IF(E42=0,"",AVERAGEIF('02 Scores'!F42:J42,">0")) | J42: =IF(E42=0,"",ROUNDUP(I42-0.5,0)) | K42: =IF(OR(C42="",D42=0),"",IF(E42=0,"No evidence",IF(H42>=3,"Contradiction",IF(H42=2,"Divergence","Agreement"))))
A43: ="K5"&IF('00 Setup'!B20="",""," · "&'00 Setup'!B20) -> K5 | B43: C1 | C43: =IF('01 Rubric'!B8="","",'01 Rubric'!B8) -> Technical accounting and IFRS application | D43: =COUNT('02 Scores'!F43:J43) -> 0 | E43: =COUNTIF('02 Scores'!F43:J43,">0") -> 0 | F43: =IF(E43=0,"",SMALL('02 Scores'!F43:J43,COUNTIF('02 Scores'!F43:J43,0)+1)) | G43: =IF(E43=0,"",MAX('02 Scores'!F43:J43)) | H43: =IF(E43=0,"",G43-F43) | I43: =IF(E43=0,"",AVERAGEIF('02 Scores'!F43:J43,">0")) | J43: =IF(E43=0,"",ROUNDUP(I43-0.5,0)) | K43: =IF(OR(C43="",D43=0),"",IF(E43=0,"No evidence",IF(H43>=3,"Contradiction",IF(H43=2,"Divergence","Agreement"))))
A44: ="K5"&IF('00 Setup'!B20="",""," · "&'00 Setup'!B20) -> K5 | B44: C2 | C44: =IF('01 Rubric'!B9="","",'01 Rubric'!B9) -> Financial reporting and close ownership | D44: =COUNT('02 Scores'!F44:J44) -> 0 | E44: =COUNTIF('02 Scores'!F44:J44,">0") -> 0 | F44: =IF(E44=0,"",SMALL('02 Scores'!F44:J44,COUNTIF('02 Scores'!F44:J44,0)+1)) | G44: =IF(E44=0,"",MAX('02 Scores'!F44:J44)) | H44: =IF(E44=0,"",G44-F44) | I44: =IF(E44=0,"",AVERAGEIF('02 Scores'!F44:J44,">0")) | J44: =IF(E44=0,"",ROUNDUP(I44-0.5,0)) | K44: =IF(OR(C44="",D44=0),"",IF(E44=0,"No evidence",IF(H44>=3,"Contradiction",IF(H44=2,"Divergence","Agreement"))))
A45: ="K5"&IF('00 Setup'!B20="",""," · "&'00 Setup'!B20) -> K5 | B45: C3 | C45: =IF('01 Rubric'!B10="","",'01 Rubric'!B10) -> Controls, compliance and audit readiness | D45: =COUNT('02 Scores'!F45:J45) -> 0 | E45: =COUNTIF('02 Scores'!F45:J45,">0") -> 0 | F45: =IF(E45=0,"",SMALL('02 Scores'!F45:J45,COUNTIF('02 Scores'!F45:J45,0)+1)) | G45: =IF(E45=0,"",MAX('02 Scores'!F45:J45)) | H45: =IF(E45=0,"",G45-F45) | I45: =IF(E45=0,"",AVERAGEIF('02 Scores'!F45:J45,">0")) | J45: =IF(E45=0,"",ROUNDUP(I45-0.5,0)) | K45: =IF(OR(C45="",D45=0),"",IF(E45=0,"No evidence",IF(H45>=3,"Contradiction",IF(H45=2,"Divergence","Agreement"))))
A46: ="K5"&IF('00 Setup'!B20="",""," · "&'00 Setup'!B20) -> K5 | B46: C4 | C46: =IF('01 Rubric'!B11="","",'01 Rubric'!B11) -> Planning, budgeting and forecasting | D46: =COUNT('02 Scores'!F46:J46) -> 0 | E46: =COUNTIF('02 Scores'!F46:J46,">0") -> 0 | F46: =IF(E46=0,"",SMALL('02 Scores'!F46:J46,COUNTIF('02 Scores'!F46:J46,0)+1)) | G46: =IF(E46=0,"",MAX('02 Scores'!F46:J46)) | H46: =IF(E46=0,"",G46-F46) | I46: =IF(E46=0,"",AVERAGEIF('02 Scores'!F46:J46,">0")) | J46: =IF(E46=0,"",ROUNDUP(I46-0.5,0)) | K46: =IF(OR(C46="",D46=0),"",IF(E46=0,"No evidence",IF(H46>=3,"Contradiction",IF(H46=2,"Divergence","Agreement"))))
A47: ="K5"&IF('00 Setup'!B20="",""," · "&'00 Setup'!B20) -> K5 | B47: C5 | C47: =IF('01 Rubric'!B12="","",'01 Rubric'!B12) -> Cash, treasury and working capital | D47: =COUNT('02 Scores'!F47:J47) -> 0 | E47: =COUNTIF('02 Scores'!F47:J47,">0") -> 0 | F47: =IF(E47=0,"",SMALL('02 Scores'!F47:J47,COUNTIF('02 Scores'!F47:J47,0)+1)) | G47: =IF(E47=0,"",MAX('02 Scores'!F47:J47)) | H47: =IF(E47=0,"",G47-F47) | I47: =IF(E47=0,"",AVERAGEIF('02 Scores'!F47:J47,">0")) | J47: =IF(E47=0,"",ROUNDUP(I47-0.5,0)) | K47: =IF(OR(C47="",D47=0),"",IF(E47=0,"No evidence",IF(H47>=3,"Contradiction",IF(H47=2,"Divergence","Agreement"))))
A48: ="K5"&IF('00 Setup'!B20="",""," · "&'00 Setup'!B20) -> K5 | B48: C6 | C48: =IF('01 Rubric'!B13="","",'01 Rubric'!B13) -> Systems, data and reporting tooling | D48: =COUNT('02 Scores'!F48:J48) -> 0 | E48: =COUNTIF('02 Scores'!F48:J48,">0") -> 0 | F48: =IF(E48=0,"",SMALL('02 Scores'!F48:J48,COUNTIF('02 Scores'!F48:J48,0)+1)) | G48: =IF(E48=0,"",MAX('02 Scores'!F48:J48)) | H48: =IF(E48=0,"",G48-F48) | I48: =IF(E48=0,"",AVERAGEIF('02 Scores'!F48:J48,">0")) | J48: =IF(E48=0,"",ROUNDUP(I48-0.5,0)) | K48: =IF(OR(C48="",D48=0),"",IF(E48=0,"No evidence",IF(H48>=3,"Contradiction",IF(H48=2,"Divergence","Agreement"))))
A49: ="K5"&IF('00 Setup'!B20="",""," · "&'00 Setup'!B20) -> K5 | B49: C7 | C49: =IF('01 Rubric'!B14="","",'01 Rubric'!B14) -> Team leadership and delegation | D49: =COUNT('02 Scores'!F49:J49) -> 0 | E49: =COUNTIF('02 Scores'!F49:J49,">0") -> 0 | F49: =IF(E49=0,"",SMALL('02 Scores'!F49:J49,COUNTIF('02 Scores'!F49:J49,0)+1)) | G49: =IF(E49=0,"",MAX('02 Scores'!F49:J49)) | H49: =IF(E49=0,"",G49-F49) | I49: =IF(E49=0,"",AVERAGEIF('02 Scores'!F49:J49,">0")) | J49: =IF(E49=0,"",ROUNDUP(I49-0.5,0)) | K49: =IF(OR(C49="",D49=0),"",IF(E49=0,"No evidence",IF(H49>=3,"Contradiction",IF(H49=2,"Divergence","Agreement"))))
A50: ="K5"&IF('00 Setup'!B20="",""," · "&'00 Setup'!B20) -> K5 | B50: C8 | C50: =IF('01 Rubric'!B15="","",'01 Rubric'!B15) -> Stakeholder communication and reporting | D50: =COUNT('02 Scores'!F50:J50) -> 0 | E50: =COUNTIF('02 Scores'!F50:J50,">0") -> 0 | F50: =IF(E50=0,"",SMALL('02 Scores'!F50:J50,COUNTIF('02 Scores'!F50:J50,0)+1)) | G50: =IF(E50=0,"",MAX('02 Scores'!F50:J50)) | H50: =IF(E50=0,"",G50-F50) | I50: =IF(E50=0,"",AVERAGEIF('02 Scores'!F50:J50,">0")) | J50: =IF(E50=0,"",ROUNDUP(I50-0.5,0)) | K50: =IF(OR(C50="",D50=0),"",IF(E50=0,"No evidence",IF(H50>=3,"Contradiction",IF(H50=2,"Divergence","Agreement"))))
A51: ="K5"&IF('00 Setup'!B20="",""," · "&'00 Setup'!B20) -> K5 | B51: C9 | C51: =IF('01 Rubric'!B16="","",'01 Rubric'!B16) -> Jurisdictional and regulatory exposure | D51: =COUNT('02 Scores'!F51:J51) -> 0 | E51: =COUNTIF('02 Scores'!F51:J51,">0") -> 0 | F51: =IF(E51=0,"",SMALL('02 Scores'!F51:J51,COUNTIF('02 Scores'!F51:J51,0)+1)) | G51: =IF(E51=0,"",MAX('02 Scores'!F51:J51)) | H51: =IF(E51=0,"",G51-F51) | I51: =IF(E51=0,"",AVERAGEIF('02 Scores'!F51:J51,">0")) | J51: =IF(E51=0,"",ROUNDUP(I51-0.5,0)) | K51: =IF(OR(C51="",D51=0),"",IF(E51=0,"No evidence",IF(H51>=3,"Contradiction",IF(H51=2,"Divergence","Agreement"))))
A52: ="K6"&IF('00 Setup'!B21="",""," · "&'00 Setup'!B21) -> K6 | B52: C1 | C52: =IF('01 Rubric'!B8="","",'01 Rubric'!B8) -> Technical accounting and IFRS application | D52: =COUNT('02 Scores'!F52:J52) -> 0 | E52: =COUNTIF('02 Scores'!F52:J52,">0") -> 0 | F52: =IF(E52=0,"",SMALL('02 Scores'!F52:J52,COUNTIF('02 Scores'!F52:J52,0)+1)) | G52: =IF(E52=0,"",MAX('02 Scores'!F52:J52)) | H52: =IF(E52=0,"",G52-F52) | I52: =IF(E52=0,"",AVERAGEIF('02 Scores'!F52:J52,">0")) | J52: =IF(E52=0,"",ROUNDUP(I52-0.5,0)) | K52: =IF(OR(C52="",D52=0),"",IF(E52=0,"No evidence",IF(H52>=3,"Contradiction",IF(H52=2,"Divergence","Agreement"))))
A53: ="K6"&IF('00 Setup'!B21="",""," · "&'00 Setup'!B21) -> K6 | B53: C2 | C53: =IF('01 Rubric'!B9="","",'01 Rubric'!B9) -> Financial reporting and close ownership | D53: =COUNT('02 Scores'!F53:J53) -> 0 | E53: =COUNTIF('02 Scores'!F53:J53,">0") -> 0 | F53: =IF(E53=0,"",SMALL('02 Scores'!F53:J53,COUNTIF('02 Scores'!F53:J53,0)+1)) | G53: =IF(E53=0,"",MAX('02 Scores'!F53:J53)) | H53: =IF(E53=0,"",G53-F53) | I53: =IF(E53=0,"",AVERAGEIF('02 Scores'!F53:J53,">0")) | J53: =IF(E53=0,"",ROUNDUP(I53-0.5,0)) | K53: =IF(OR(C53="",D53=0),"",IF(E53=0,"No evidence",IF(H53>=3,"Contradiction",IF(H53=2,"Divergence","Agreement"))))
A54: ="K6"&IF('00 Setup'!B21="",""," · "&'00 Setup'!B21) -> K6 | B54: C3 | C54: =IF('01 Rubric'!B10="","",'01 Rubric'!B10) -> Controls, compliance and audit readiness | D54: =COUNT('02 Scores'!F54:J54) -> 0 | E54: =COUNTIF('02 Scores'!F54:J54,">0") -> 0 | F54: =IF(E54=0,"",SMALL('02 Scores'!F54:J54,COUNTIF('02 Scores'!F54:J54,0)+1)) | G54: =IF(E54=0,"",MAX('02 Scores'!F54:J54)) | H54: =IF(E54=0,"",G54-F54) | I54: =IF(E54=0,"",AVERAGEIF('02 Scores'!F54:J54,">0")) | J54: =IF(E54=0,"",ROUNDUP(I54-0.5,0)) | K54: =IF(OR(C54="",D54=0),"",IF(E54=0,"No evidence",IF(H54>=3,"Contradiction",IF(H54=2,"Divergence","Agreement"))))
A55: ="K6"&IF('00 Setup'!B21="",""," · "&'00 Setup'!B21) -> K6 | B55: C4 | C55: =IF('01 Rubric'!B11="","",'01 Rubric'!B11) -> Planning, budgeting and forecasting | D55: =COUNT('02 Scores'!F55:J55) -> 0 | E55: =COUNTIF('02 Scores'!F55:J55,">0") -> 0 | F55: =IF(E55=0,"",SMALL('02 Scores'!F55:J55,COUNTIF('02 Scores'!F55:J55,0)+1)) | G55: =IF(E55=0,"",MAX('02 Scores'!F55:J55)) | H55: =IF(E55=0,"",G55-F55) | I55: =IF(E55=0,"",AVERAGEIF('02 Scores'!F55:J55,">0")) | J55: =IF(E55=0,"",ROUNDUP(I55-0.5,0)) | K55: =IF(OR(C55="",D55=0),"",IF(E55=0,"No evidence",IF(H55>=3,"Contradiction",IF(H55=2,"Divergence","Agreement"))))
A56: ="K6"&IF('00 Setup'!B21="",""," · "&'00 Setup'!B21) -> K6 | B56: C5 | C56: =IF('01 Rubric'!B12="","",'01 Rubric'!B12) -> Cash, treasury and working capital | D56: =COUNT('02 Scores'!F56:J56) -> 0 | E56: =COUNTIF('02 Scores'!F56:J56,">0") -> 0 | F56: =IF(E56=0,"",SMALL('02 Scores'!F56:J56,COUNTIF('02 Scores'!F56:J56,0)+1)) | G56: =IF(E56=0,"",MAX('02 Scores'!F56:J56)) | H56: =IF(E56=0,"",G56-F56) | I56: =IF(E56=0,"",AVERAGEIF('02 Scores'!F56:J56,">0")) | J56: =IF(E56=0,"",ROUNDUP(I56-0.5,0)) | K56: =IF(OR(C56="",D56=0),"",IF(E56=0,"No evidence",IF(H56>=3,"Contradiction",IF(H56=2,"Divergence","Agreement"))))
A57: ="K6"&IF('00 Setup'!B21="",""," · "&'00 Setup'!B21) -> K6 | B57: C6 | C57: =IF('01 Rubric'!B13="","",'01 Rubric'!B13) -> Systems, data and reporting tooling | D57: =COUNT('02 Scores'!F57:J57) -> 0 | E57: =COUNTIF('02 Scores'!F57:J57,">0") -> 0 | F57: =IF(E57=0,"",SMALL('02 Scores'!F57:J57,COUNTIF('02 Scores'!F57:J57,0)+1)) | G57: =IF(E57=0,"",MAX('02 Scores'!F57:J57)) | H57: =IF(E57=0,"",G57-F57) | I57: =IF(E57=0,"",AVERAGEIF('02 Scores'!F57:J57,">0")) | J57: =IF(E57=0,"",ROUNDUP(I57-0.5,0)) | K57: =IF(OR(C57="",D57=0),"",IF(E57=0,"No evidence",IF(H57>=3,"Contradiction",IF(H57=2,"Divergence","Agreement"))))
A58: ="K6"&IF('00 Setup'!B21="",""," · "&'00 Setup'!B21) -> K6 | B58: C7 | C58: =IF('01 Rubric'!B14="","",'01 Rubric'!B14) -> Team leadership and delegation | D58: =COUNT('02 Scores'!F58:J58) -> 0 | E58: =COUNTIF('02 Scores'!F58:J58,">0") -> 0 | F58: =IF(E58=0,"",SMALL('02 Scores'!F58:J58,COUNTIF('02 Scores'!F58:J58,0)+1)) | G58: =IF(E58=0,"",MAX('02 Scores'!F58:J58)) | H58: =IF(E58=0,"",G58-F58) | I58: =IF(E58=0,"",AVERAGEIF('02 Scores'!F58:J58,">0")) | J58: =IF(E58=0,"",ROUNDUP(I58-0.5,0)) | K58: =IF(OR(C58="",D58=0),"",IF(E58=0,"No evidence",IF(H58>=3,"Contradiction",IF(H58=2,"Divergence","Agreement"))))
A59: ="K6"&IF('00 Setup'!B21="",""," · "&'00 Setup'!B21) -> K6 | B59: C8 | C59: =IF('01 Rubric'!B15="","",'01 Rubric'!B15) -> Stakeholder communication and reporting | D59: =COUNT('02 Scores'!F59:J59) -> 0 | E59: =COUNTIF('02 Scores'!F59:J59,">0") -> 0 | F59: =IF(E59=0,"",SMALL('02 Scores'!F59:J59,COUNTIF('02 Scores'!F59:J59,0)+1)) | G59: =IF(E59=0,"",MAX('02 Scores'!F59:J59)) | H59: =IF(E59=0,"",G59-F59) | I59: =IF(E59=0,"",AVERAGEIF('02 Scores'!F59:J59,">0")) | J59: =IF(E59=0,"",ROUNDUP(I59-0.5,0)) | K59: =IF(OR(C59="",D59=0),"",IF(E59=0,"No evidence",IF(H59>=3,"Contradiction",IF(H59=2,"Divergence","Agreement"))))
A60: ="K6"&IF('00 Setup'!B21="",""," · "&'00 Setup'!B21) -> K6 | B60: C9 | C60: =IF('01 Rubric'!B16="","",'01 Rubric'!B16) -> Jurisdictional and regulatory exposure | D60: =COUNT('02 Scores'!F60:J60) -> 0 | E60: =COUNTIF('02 Scores'!F60:J60,">0") -> 0 | F60: =IF(E60=0,"",SMALL('02 Scores'!F60:J60,COUNTIF('02 Scores'!F60:J60,0)+1)) | G60: =IF(E60=0,"",MAX('02 Scores'!F60:J60)) | H60: =IF(E60=0,"",G60-F60) | I60: =IF(E60=0,"",AVERAGEIF('02 Scores'!F60:J60,">0")) | J60: =IF(E60=0,"",ROUNDUP(I60-0.5,0)) | K60: =IF(OR(C60="",D60=0),"",IF(E60=0,"No evidence",IF(H60>=3,"Contradiction",IF(H60=2,"Divergence","Agreement"))))
C62: Divergences (spread 2) | D62: =COUNTIF(K7:K60,"Divergence") -> 0
C63: Contradictions (spread 3 or 4) | D63: =COUNTIF(K7:K60,"Contradiction") -> 0
C64: No evidence | D64: =COUNTIF(K7:K60,"No evidence") -> 0
C65: Reviewer agreement (spread 0 or 1) | D65: =IF(COUNTIF(K7:K60,"?*")-D64=0,"",COUNTIF(K7:K60,"Agreement")/(COUNTIF(K7:K60,"?*")-D64)) | E65: =IF(D65="","",IF(D65>=0.8,"High",IF(D65>=0.6,"Medium","Low")))

Sheet 04 Calibration
A1: CALIBRE BY DAFTAR
A2: 04 · Calibration
A3: Resolve every flagged cell in the session: an agreed score and a written reason naming the evidence that settled it. Unresolved cells keep the panel mean.
A6: Finalist | B6: Ref | C6: Criterion | D6: Flag | E6: Spread | F6: Provisional | G6: Calibrated score | H6: Reason recorded | I6: Final | J6: Status
A7: ="K1"&IF('00 Setup'!B16="",""," · "&'00 Setup'!B16) -> K1 | B7: C1 | C7: =IF('01 Rubric'!B8="","",'01 Rubric'!B8) -> Technical accounting and IFRS application | D7: ='03 Divergence'!K7 | E7: ='03 Divergence'!H7 | F7: ='03 Divergence'!J7 | I7: =IF(D7="","",IF(D7="No evidence",0,IF(OR(D7="Divergence",D7="Contradiction"),IF(G7="",F7,G7),F7))) | J7: =IF(D7="","",IF(D7="No evidence","No evidence",IF(OR(D7="Divergence",D7="Contradiction"),IF(G7="","Unresolved",IF(H7="","Reason missing","Calibrated")),"Agreement")))
A8: ="K1"&IF('00 Setup'!B16="",""," · "&'00 Setup'!B16) -> K1 | B8: C2 | C8: =IF('01 Rubric'!B9="","",'01 Rubric'!B9) -> Financial reporting and close ownership | D8: ='03 Divergence'!K8 | E8: ='03 Divergence'!H8 | F8: ='03 Divergence'!J8 | I8: =IF(D8="","",IF(D8="No evidence",0,IF(OR(D8="Divergence",D8="Contradiction"),IF(G8="",F8,G8),F8))) | J8: =IF(D8="","",IF(D8="No evidence","No evidence",IF(OR(D8="Divergence",D8="Contradiction"),IF(G8="","Unresolved",IF(H8="","Reason missing","Calibrated")),"Agreement")))
A9: ="K1"&IF('00 Setup'!B16="",""," · "&'00 Setup'!B16) -> K1 | B9: C3 | C9: =IF('01 Rubric'!B10="","",'01 Rubric'!B10) -> Controls, compliance and audit readiness | D9: ='03 Divergence'!K9 | E9: ='03 Divergence'!H9 | F9: ='03 Divergence'!J9 | I9: =IF(D9="","",IF(D9="No evidence",0,IF(OR(D9="Divergence",D9="Contradiction"),IF(G9="",F9,G9),F9))) | J9: =IF(D9="","",IF(D9="No evidence","No evidence",IF(OR(D9="Divergence",D9="Contradiction"),IF(G9="","Unresolved",IF(H9="","Reason missing","Calibrated")),"Agreement")))
A10: ="K1"&IF('00 Setup'!B16="",""," · "&'00 Setup'!B16) -> K1 | B10: C4 | C10: =IF('01 Rubric'!B11="","",'01 Rubric'!B11) -> Planning, budgeting and forecasting | D10: ='03 Divergence'!K10 | E10: ='03 Divergence'!H10 | F10: ='03 Divergence'!J10 | I10: =IF(D10="","",IF(D10="No evidence",0,IF(OR(D10="Divergence",D10="Contradiction"),IF(G10="",F10,G10),F10))) | J10: =IF(D10="","",IF(D10="No evidence","No evidence",IF(OR(D10="Divergence",D10="Contradiction"),IF(G10="","Unresolved",IF(H10="","Reason missing","Calibrated")),"Agreement")))
A11: ="K1"&IF('00 Setup'!B16="",""," · "&'00 Setup'!B16) -> K1 | B11: C5 | C11: =IF('01 Rubric'!B12="","",'01 Rubric'!B12) -> Cash, treasury and working capital | D11: ='03 Divergence'!K11 | E11: ='03 Divergence'!H11 | F11: ='03 Divergence'!J11 | I11: =IF(D11="","",IF(D11="No evidence",0,IF(OR(D11="Divergence",D11="Contradiction"),IF(G11="",F11,G11),F11))) | J11: =IF(D11="","",IF(D11="No evidence","No evidence",IF(OR(D11="Divergence",D11="Contradiction"),IF(G11="","Unresolved",IF(H11="","Reason missing","Calibrated")),"Agreement")))
A12: ="K1"&IF('00 Setup'!B16="",""," · "&'00 Setup'!B16) -> K1 | B12: C6 | C12: =IF('01 Rubric'!B13="","",'01 Rubric'!B13) -> Systems, data and reporting tooling | D12: ='03 Divergence'!K12 | E12: ='03 Divergence'!H12 | F12: ='03 Divergence'!J12 | I12: =IF(D12="","",IF(D12="No evidence",0,IF(OR(D12="Divergence",D12="Contradiction"),IF(G12="",F12,G12),F12))) | J12: =IF(D12="","",IF(D12="No evidence","No evidence",IF(OR(D12="Divergence",D12="Contradiction"),IF(G12="","Unresolved",IF(H12="","Reason missing","Calibrated")),"Agreement")))
A13: ="K1"&IF('00 Setup'!B16="",""," · "&'00 Setup'!B16) -> K1 | B13: C7 | C13: =IF('01 Rubric'!B14="","",'01 Rubric'!B14) -> Team leadership and delegation | D13: ='03 Divergence'!K13 | E13: ='03 Divergence'!H13 | F13: ='03 Divergence'!J13 | I13: =IF(D13="","",IF(D13="No evidence",0,IF(OR(D13="Divergence",D13="Contradiction"),IF(G13="",F13,G13),F13))) | J13: =IF(D13="","",IF(D13="No evidence","No evidence",IF(OR(D13="Divergence",D13="Contradiction"),IF(G13="","Unresolved",IF(H13="","Reason missing","Calibrated")),"Agreement")))
A14: ="K1"&IF('00 Setup'!B16="",""," · "&'00 Setup'!B16) -> K1 | B14: C8 | C14: =IF('01 Rubric'!B15="","",'01 Rubric'!B15) -> Stakeholder communication and reporting | D14: ='03 Divergence'!K14 | E14: ='03 Divergence'!H14 | F14: ='03 Divergence'!J14 | I14: =IF(D14="","",IF(D14="No evidence",0,IF(OR(D14="Divergence",D14="Contradiction"),IF(G14="",F14,G14),F14))) | J14: =IF(D14="","",IF(D14="No evidence","No evidence",IF(OR(D14="Divergence",D14="Contradiction"),IF(G14="","Unresolved",IF(H14="","Reason missing","Calibrated")),"Agreement")))
A15: ="K1"&IF('00 Setup'!B16="",""," · "&'00 Setup'!B16) -> K1 | B15: C9 | C15: =IF('01 Rubric'!B16="","",'01 Rubric'!B16) -> Jurisdictional and regulatory exposure | D15: ='03 Divergence'!K15 | E15: ='03 Divergence'!H15 | F15: ='03 Divergence'!J15 | I15: =IF(D15="","",IF(D15="No evidence",0,IF(OR(D15="Divergence",D15="Contradiction"),IF(G15="",F15,G15),F15))) | J15: =IF(D15="","",IF(D15="No evidence","No evidence",IF(OR(D15="Divergence",D15="Contradiction"),IF(G15="","Unresolved",IF(H15="","Reason missing","Calibrated")),"Agreement")))
A16: ="K2"&IF('00 Setup'!B17="",""," · "&'00 Setup'!B17) -> K2 | B16: C1 | C16: =IF('01 Rubric'!B8="","",'01 Rubric'!B8) -> Technical accounting and IFRS application | D16: ='03 Divergence'!K16 | E16: ='03 Divergence'!H16 | F16: ='03 Divergence'!J16 | I16: =IF(D16="","",IF(D16="No evidence",0,IF(OR(D16="Divergence",D16="Contradiction"),IF(G16="",F16,G16),F16))) | J16: =IF(D16="","",IF(D16="No evidence","No evidence",IF(OR(D16="Divergence",D16="Contradiction"),IF(G16="","Unresolved",IF(H16="","Reason missing","Calibrated")),"Agreement")))
A17: ="K2"&IF('00 Setup'!B17="",""," · "&'00 Setup'!B17) -> K2 | B17: C2 | C17: =IF('01 Rubric'!B9="","",'01 Rubric'!B9) -> Financial reporting and close ownership | D17: ='03 Divergence'!K17 | E17: ='03 Divergence'!H17 | F17: ='03 Divergence'!J17 | I17: =IF(D17="","",IF(D17="No evidence",0,IF(OR(D17="Divergence",D17="Contradiction"),IF(G17="",F17,G17),F17))) | J17: =IF(D17="","",IF(D17="No evidence","No evidence",IF(OR(D17="Divergence",D17="Contradiction"),IF(G17="","Unresolved",IF(H17="","Reason missing","Calibrated")),"Agreement")))
A18: ="K2"&IF('00 Setup'!B17="",""," · "&'00 Setup'!B17) -> K2 | B18: C3 | C18: =IF('01 Rubric'!B10="","",'01 Rubric'!B10) -> Controls, compliance and audit readiness | D18: ='03 Divergence'!K18 | E18: ='03 Divergence'!H18 | F18: ='03 Divergence'!J18 | I18: =IF(D18="","",IF(D18="No evidence",0,IF(OR(D18="Divergence",D18="Contradiction"),IF(G18="",F18,G18),F18))) | J18: =IF(D18="","",IF(D18="No evidence","No evidence",IF(OR(D18="Divergence",D18="Contradiction"),IF(G18="","Unresolved",IF(H18="","Reason missing","Calibrated")),"Agreement")))
A19: ="K2"&IF('00 Setup'!B17="",""," · "&'00 Setup'!B17) -> K2 | B19: C4 | C19: =IF('01 Rubric'!B11="","",'01 Rubric'!B11) -> Planning, budgeting and forecasting | D19: ='03 Divergence'!K19 | E19: ='03 Divergence'!H19 | F19: ='03 Divergence'!J19 | I19: =IF(D19="","",IF(D19="No evidence",0,IF(OR(D19="Divergence",D19="Contradiction"),IF(G19="",F19,G19),F19))) | J19: =IF(D19="","",IF(D19="No evidence","No evidence",IF(OR(D19="Divergence",D19="Contradiction"),IF(G19="","Unresolved",IF(H19="","Reason missing","Calibrated")),"Agreement")))
A20: ="K2"&IF('00 Setup'!B17="",""," · "&'00 Setup'!B17) -> K2 | B20: C5 | C20: =IF('01 Rubric'!B12="","",'01 Rubric'!B12) -> Cash, treasury and working capital | D20: ='03 Divergence'!K20 | E20: ='03 Divergence'!H20 | F20: ='03 Divergence'!J20 | I20: =IF(D20="","",IF(D20="No evidence",0,IF(OR(D20="Divergence",D20="Contradiction"),IF(G20="",F20,G20),F20))) | J20: =IF(D20="","",IF(D20="No evidence","No evidence",IF(OR(D20="Divergence",D20="Contradiction"),IF(G20="","Unresolved",IF(H20="","Reason missing","Calibrated")),"Agreement")))
A21: ="K2"&IF('00 Setup'!B17="",""," · "&'00 Setup'!B17) -> K2 | B21: C6 | C21: =IF('01 Rubric'!B13="","",'01 Rubric'!B13) -> Systems, data and reporting tooling | D21: ='03 Divergence'!K21 | E21: ='03 Divergence'!H21 | F21: ='03 Divergence'!J21 | I21: =IF(D21="","",IF(D21="No evidence",0,IF(OR(D21="Divergence",D21="Contradiction"),IF(G21="",F21,G21),F21))) | J21: =IF(D21="","",IF(D21="No evidence","No evidence",IF(OR(D21="Divergence",D21="Contradiction"),IF(G21="","Unresolved",IF(H21="","Reason missing","Calibrated")),"Agreement")))
A22: ="K2"&IF('00 Setup'!B17="",""," · "&'00 Setup'!B17) -> K2 | B22: C7 | C22: =IF('01 Rubric'!B14="","",'01 Rubric'!B14) -> Team leadership and delegation | D22: ='03 Divergence'!K22 | E22: ='03 Divergence'!H22 | F22: ='03 Divergence'!J22 | I22: =IF(D22="","",IF(D22="No evidence",0,IF(OR(D22="Divergence",D22="Contradiction"),IF(G22="",F22,G22),F22))) | J22: =IF(D22="","",IF(D22="No evidence","No evidence",IF(OR(D22="Divergence",D22="Contradiction"),IF(G22="","Unresolved",IF(H22="","Reason missing","Calibrated")),"Agreement")))
A23: ="K2"&IF('00 Setup'!B17="",""," · "&'00 Setup'!B17) -> K2 | B23: C8 | C23: =IF('01 Rubric'!B15="","",'01 Rubric'!B15) -> Stakeholder communication and reporting | D23: ='03 Divergence'!K23 | E23: ='03 Divergence'!H23 | F23: ='03 Divergence'!J23 | I23: =IF(D23="","",IF(D23="No evidence",0,IF(OR(D23="Divergence",D23="Contradiction"),IF(G23="",F23,G23),F23))) | J23: =IF(D23="","",IF(D23="No evidence","No evidence",IF(OR(D23="Divergence",D23="Contradiction"),IF(G23="","Unresolved",IF(H23="","Reason missing","Calibrated")),"Agreement")))
A24: ="K2"&IF('00 Setup'!B17="",""," · "&'00 Setup'!B17) -> K2 | B24: C9 | C24: =IF('01 Rubric'!B16="","",'01 Rubric'!B16) -> Jurisdictional and regulatory exposure | D24: ='03 Divergence'!K24 | E24: ='03 Divergence'!H24 | F24: ='03 Divergence'!J24 | I24: =IF(D24="","",IF(D24="No evidence",0,IF(OR(D24="Divergence",D24="Contradiction"),IF(G24="",F24,G24),F24))) | J24: =IF(D24="","",IF(D24="No evidence","No evidence",IF(OR(D24="Divergence",D24="Contradiction"),IF(G24="","Unresolved",IF(H24="","Reason missing","Calibrated")),"Agreement")))
A25: ="K3"&IF('00 Setup'!B18="",""," · "&'00 Setup'!B18) -> K3 | B25: C1 | C25: =IF('01 Rubric'!B8="","",'01 Rubric'!B8) -> Technical accounting and IFRS application | D25: ='03 Divergence'!K25 | E25: ='03 Divergence'!H25 | F25: ='03 Divergence'!J25 | I25: =IF(D25="","",IF(D25="No evidence",0,IF(OR(D25="Divergence",D25="Contradiction"),IF(G25="",F25,G25),F25))) | J25: =IF(D25="","",IF(D25="No evidence","No evidence",IF(OR(D25="Divergence",D25="Contradiction"),IF(G25="","Unresolved",IF(H25="","Reason missing","Calibrated")),"Agreement")))
A26: ="K3"&IF('00 Setup'!B18="",""," · "&'00 Setup'!B18) -> K3 | B26: C2 | C26: =IF('01 Rubric'!B9="","",'01 Rubric'!B9) -> Financial reporting and close ownership | D26: ='03 Divergence'!K26 | E26: ='03 Divergence'!H26 | F26: ='03 Divergence'!J26 | I26: =IF(D26="","",IF(D26="No evidence",0,IF(OR(D26="Divergence",D26="Contradiction"),IF(G26="",F26,G26),F26))) | J26: =IF(D26="","",IF(D26="No evidence","No evidence",IF(OR(D26="Divergence",D26="Contradiction"),IF(G26="","Unresolved",IF(H26="","Reason missing","Calibrated")),"Agreement")))
A27: ="K3"&IF('00 Setup'!B18="",""," · "&'00 Setup'!B18) -> K3 | B27: C3 | C27: =IF('01 Rubric'!B10="","",'01 Rubric'!B10) -> Controls, compliance and audit readiness | D27: ='03 Divergence'!K27 | E27: ='03 Divergence'!H27 | F27: ='03 Divergence'!J27 | I27: =IF(D27="","",IF(D27="No evidence",0,IF(OR(D27="Divergence",D27="Contradiction"),IF(G27="",F27,G27),F27))) | J27: =IF(D27="","",IF(D27="No evidence","No evidence",IF(OR(D27="Divergence",D27="Contradiction"),IF(G27="","Unresolved",IF(H27="","Reason missing","Calibrated")),"Agreement")))
A28: ="K3"&IF('00 Setup'!B18="",""," · "&'00 Setup'!B18) -> K3 | B28: C4 | C28: =IF('01 Rubric'!B11="","",'01 Rubric'!B11) -> Planning, budgeting and forecasting | D28: ='03 Divergence'!K28 | E28: ='03 Divergence'!H28 | F28: ='03 Divergence'!J28 | I28: =IF(D28="","",IF(D28="No evidence",0,IF(OR(D28="Divergence",D28="Contradiction"),IF(G28="",F28,G28),F28))) | J28: =IF(D28="","",IF(D28="No evidence","No evidence",IF(OR(D28="Divergence",D28="Contradiction"),IF(G28="","Unresolved",IF(H28="","Reason missing","Calibrated")),"Agreement")))
A29: ="K3"&IF('00 Setup'!B18="",""," · "&'00 Setup'!B18) -> K3 | B29: C5 | C29: =IF('01 Rubric'!B12="","",'01 Rubric'!B12) -> Cash, treasury and working capital | D29: ='03 Divergence'!K29 | E29: ='03 Divergence'!H29 | F29: ='03 Divergence'!J29 | I29: =IF(D29="","",IF(D29="No evidence",0,IF(OR(D29="Divergence",D29="Contradiction"),IF(G29="",F29,G29),F29))) | J29: =IF(D29="","",IF(D29="No evidence","No evidence",IF(OR(D29="Divergence",D29="Contradiction"),IF(G29="","Unresolved",IF(H29="","Reason missing","Calibrated")),"Agreement")))
A30: ="K3"&IF('00 Setup'!B18="",""," · "&'00 Setup'!B18) -> K3 | B30: C6 | C30: =IF('01 Rubric'!B13="","",'01 Rubric'!B13) -> Systems, data and reporting tooling | D30: ='03 Divergence'!K30 | E30: ='03 Divergence'!H30 | F30: ='03 Divergence'!J30 | I30: =IF(D30="","",IF(D30="No evidence",0,IF(OR(D30="Divergence",D30="Contradiction"),IF(G30="",F30,G30),F30))) | J30: =IF(D30="","",IF(D30="No evidence","No evidence",IF(OR(D30="Divergence",D30="Contradiction"),IF(G30="","Unresolved",IF(H30="","Reason missing","Calibrated")),"Agreement")))
A31: ="K3"&IF('00 Setup'!B18="",""," · "&'00 Setup'!B18) -> K3 | B31: C7 | C31: =IF('01 Rubric'!B14="","",'01 Rubric'!B14) -> Team leadership and delegation | D31: ='03 Divergence'!K31 | E31: ='03 Divergence'!H31 | F31: ='03 Divergence'!J31 | I31: =IF(D31="","",IF(D31="No evidence",0,IF(OR(D31="Divergence",D31="Contradiction"),IF(G31="",F31,G31),F31))) | J31: =IF(D31="","",IF(D31="No evidence","No evidence",IF(OR(D31="Divergence",D31="Contradiction"),IF(G31="","Unresolved",IF(H31="","Reason missing","Calibrated")),"Agreement")))
A32: ="K3"&IF('00 Setup'!B18="",""," · "&'00 Setup'!B18) -> K3 | B32: C8 | C32: =IF('01 Rubric'!B15="","",'01 Rubric'!B15) -> Stakeholder communication and reporting | D32: ='03 Divergence'!K32 | E32: ='03 Divergence'!H32 | F32: ='03 Divergence'!J32 | I32: =IF(D32="","",IF(D32="No evidence",0,IF(OR(D32="Divergence",D32="Contradiction"),IF(G32="",F32,G32),F32))) | J32: =IF(D32="","",IF(D32="No evidence","No evidence",IF(OR(D32="Divergence",D32="Contradiction"),IF(G32="","Unresolved",IF(H32="","Reason missing","Calibrated")),"Agreement")))
A33: ="K3"&IF('00 Setup'!B18="",""," · "&'00 Setup'!B18) -> K3 | B33: C9 | C33: =IF('01 Rubric'!B16="","",'01 Rubric'!B16) -> Jurisdictional and regulatory exposure | D33: ='03 Divergence'!K33 | E33: ='03 Divergence'!H33 | F33: ='03 Divergence'!J33 | I33: =IF(D33="","",IF(D33="No evidence",0,IF(OR(D33="Divergence",D33="Contradiction"),IF(G33="",F33,G33),F33))) | J33: =IF(D33="","",IF(D33="No evidence","No evidence",IF(OR(D33="Divergence",D33="Contradiction"),IF(G33="","Unresolved",IF(H33="","Reason missing","Calibrated")),"Agreement")))
A34: ="K4"&IF('00 Setup'!B19="",""," · "&'00 Setup'!B19) -> K4 | B34: C1 | C34: =IF('01 Rubric'!B8="","",'01 Rubric'!B8) -> Technical accounting and IFRS application | D34: ='03 Divergence'!K34 | E34: ='03 Divergence'!H34 | F34: ='03 Divergence'!J34 | I34: =IF(D34="","",IF(D34="No evidence",0,IF(OR(D34="Divergence",D34="Contradiction"),IF(G34="",F34,G34),F34))) | J34: =IF(D34="","",IF(D34="No evidence","No evidence",IF(OR(D34="Divergence",D34="Contradiction"),IF(G34="","Unresolved",IF(H34="","Reason missing","Calibrated")),"Agreement")))
A35: ="K4"&IF('00 Setup'!B19="",""," · "&'00 Setup'!B19) -> K4 | B35: C2 | C35: =IF('01 Rubric'!B9="","",'01 Rubric'!B9) -> Financial reporting and close ownership | D35: ='03 Divergence'!K35 | E35: ='03 Divergence'!H35 | F35: ='03 Divergence'!J35 | I35: =IF(D35="","",IF(D35="No evidence",0,IF(OR(D35="Divergence",D35="Contradiction"),IF(G35="",F35,G35),F35))) | J35: =IF(D35="","",IF(D35="No evidence","No evidence",IF(OR(D35="Divergence",D35="Contradiction"),IF(G35="","Unresolved",IF(H35="","Reason missing","Calibrated")),"Agreement")))
A36: ="K4"&IF('00 Setup'!B19="",""," · "&'00 Setup'!B19) -> K4 | B36: C3 | C36: =IF('01 Rubric'!B10="","",'01 Rubric'!B10) -> Controls, compliance and audit readiness | D36: ='03 Divergence'!K36 | E36: ='03 Divergence'!H36 | F36: ='03 Divergence'!J36 | I36: =IF(D36="","",IF(D36="No evidence",0,IF(OR(D36="Divergence",D36="Contradiction"),IF(G36="",F36,G36),F36))) | J36: =IF(D36="","",IF(D36="No evidence","No evidence",IF(OR(D36="Divergence",D36="Contradiction"),IF(G36="","Unresolved",IF(H36="","Reason missing","Calibrated")),"Agreement")))
A37: ="K4"&IF('00 Setup'!B19="",""," · "&'00 Setup'!B19) -> K4 | B37: C4 | C37: =IF('01 Rubric'!B11="","",'01 Rubric'!B11) -> Planning, budgeting and forecasting | D37: ='03 Divergence'!K37 | E37: ='03 Divergence'!H37 | F37: ='03 Divergence'!J37 | I37: =IF(D37="","",IF(D37="No evidence",0,IF(OR(D37="Divergence",D37="Contradiction"),IF(G37="",F37,G37),F37))) | J37: =IF(D37="","",IF(D37="No evidence","No evidence",IF(OR(D37="Divergence",D37="Contradiction"),IF(G37="","Unresolved",IF(H37="","Reason missing","Calibrated")),"Agreement")))
A38: ="K4"&IF('00 Setup'!B19="",""," · "&'00 Setup'!B19) -> K4 | B38: C5 | C38: =IF('01 Rubric'!B12="","",'01 Rubric'!B12) -> Cash, treasury and working capital | D38: ='03 Divergence'!K38 | E38: ='03 Divergence'!H38 | F38: ='03 Divergence'!J38 | I38: =IF(D38="","",IF(D38="No evidence",0,IF(OR(D38="Divergence",D38="Contradiction"),IF(G38="",F38,G38),F38))) | J38: =IF(D38="","",IF(D38="No evidence","No evidence",IF(OR(D38="Divergence",D38="Contradiction"),IF(G38="","Unresolved",IF(H38="","Reason missing","Calibrated")),"Agreement")))
A39: ="K4"&IF('00 Setup'!B19="",""," · "&'00 Setup'!B19) -> K4 | B39: C6 | C39: =IF('01 Rubric'!B13="","",'01 Rubric'!B13) -> Systems, data and reporting tooling | D39: ='03 Divergence'!K39 | E39: ='03 Divergence'!H39 | F39: ='03 Divergence'!J39 | I39: =IF(D39="","",IF(D39="No evidence",0,IF(OR(D39="Divergence",D39="Contradiction"),IF(G39="",F39,G39),F39))) | J39: =IF(D39="","",IF(D39="No evidence","No evidence",IF(OR(D39="Divergence",D39="Contradiction"),IF(G39="","Unresolved",IF(H39="","Reason missing","Calibrated")),"Agreement")))
A40: ="K4"&IF('00 Setup'!B19="",""," · "&'00 Setup'!B19) -> K4 | B40: C7 | C40: =IF('01 Rubric'!B14="","",'01 Rubric'!B14) -> Team leadership and delegation | D40: ='03 Divergence'!K40 | E40: ='03 Divergence'!H40 | F40: ='03 Divergence'!J40 | I40: =IF(D40="","",IF(D40="No evidence",0,IF(OR(D40="Divergence",D40="Contradiction"),IF(G40="",F40,G40),F40))) | J40: =IF(D40="","",IF(D40="No evidence","No evidence",IF(OR(D40="Divergence",D40="Contradiction"),IF(G40="","Unresolved",IF(H40="","Reason missing","Calibrated")),"Agreement")))
A41: ="K4"&IF('00 Setup'!B19="",""," · "&'00 Setup'!B19) -> K4 | B41: C8 | C41: =IF('01 Rubric'!B15="","",'01 Rubric'!B15) -> Stakeholder communication and reporting | D41: ='03 Divergence'!K41 | E41: ='03 Divergence'!H41 | F41: ='03 Divergence'!J41 | I41: =IF(D41="","",IF(D41="No evidence",0,IF(OR(D41="Divergence",D41="Contradiction"),IF(G41="",F41,G41),F41))) | J41: =IF(D41="","",IF(D41="No evidence","No evidence",IF(OR(D41="Divergence",D41="Contradiction"),IF(G41="","Unresolved",IF(H41="","Reason missing","Calibrated")),"Agreement")))
A42: ="K4"&IF('00 Setup'!B19="",""," · "&'00 Setup'!B19) -> K4 | B42: C9 | C42: =IF('01 Rubric'!B16="","",'01 Rubric'!B16) -> Jurisdictional and regulatory exposure | D42: ='03 Divergence'!K42 | E42: ='03 Divergence'!H42 | F42: ='03 Divergence'!J42 | I42: =IF(D42="","",IF(D42="No evidence",0,IF(OR(D42="Divergence",D42="Contradiction"),IF(G42="",F42,G42),F42))) | J42: =IF(D42="","",IF(D42="No evidence","No evidence",IF(OR(D42="Divergence",D42="Contradiction"),IF(G42="","Unresolved",IF(H42="","Reason missing","Calibrated")),"Agreement")))
A43: ="K5"&IF('00 Setup'!B20="",""," · "&'00 Setup'!B20) -> K5 | B43: C1 | C43: =IF('01 Rubric'!B8="","",'01 Rubric'!B8) -> Technical accounting and IFRS application | D43: ='03 Divergence'!K43 | E43: ='03 Divergence'!H43 | F43: ='03 Divergence'!J43 | I43: =IF(D43="","",IF(D43="No evidence",0,IF(OR(D43="Divergence",D43="Contradiction"),IF(G43="",F43,G43),F43))) | J43: =IF(D43="","",IF(D43="No evidence","No evidence",IF(OR(D43="Divergence",D43="Contradiction"),IF(G43="","Unresolved",IF(H43="","Reason missing","Calibrated")),"Agreement")))
A44: ="K5"&IF('00 Setup'!B20="",""," · "&'00 Setup'!B20) -> K5 | B44: C2 | C44: =IF('01 Rubric'!B9="","",'01 Rubric'!B9) -> Financial reporting and close ownership | D44: ='03 Divergence'!K44 | E44: ='03 Divergence'!H44 | F44: ='03 Divergence'!J44 | I44: =IF(D44="","",IF(D44="No evidence",0,IF(OR(D44="Divergence",D44="Contradiction"),IF(G44="",F44,G44),F44))) | J44: =IF(D44="","",IF(D44="No evidence","No evidence",IF(OR(D44="Divergence",D44="Contradiction"),IF(G44="","Unresolved",IF(H44="","Reason missing","Calibrated")),"Agreement")))
A45: ="K5"&IF('00 Setup'!B20="",""," · "&'00 Setup'!B20) -> K5 | B45: C3 | C45: =IF('01 Rubric'!B10="","",'01 Rubric'!B10) -> Controls, compliance and audit readiness | D45: ='03 Divergence'!K45 | E45: ='03 Divergence'!H45 | F45: ='03 Divergence'!J45 | I45: =IF(D45="","",IF(D45="No evidence",0,IF(OR(D45="Divergence",D45="Contradiction"),IF(G45="",F45,G45),F45))) | J45: =IF(D45="","",IF(D45="No evidence","No evidence",IF(OR(D45="Divergence",D45="Contradiction"),IF(G45="","Unresolved",IF(H45="","Reason missing","Calibrated")),"Agreement")))
A46: ="K5"&IF('00 Setup'!B20="",""," · "&'00 Setup'!B20) -> K5 | B46: C4 | C46: =IF('01 Rubric'!B11="","",'01 Rubric'!B11) -> Planning, budgeting and forecasting | D46: ='03 Divergence'!K46 | E46: ='03 Divergence'!H46 | F46: ='03 Divergence'!J46 | I46: =IF(D46="","",IF(D46="No evidence",0,IF(OR(D46="Divergence",D46="Contradiction"),IF(G46="",F46,G46),F46))) | J46: =IF(D46="","",IF(D46="No evidence","No evidence",IF(OR(D46="Divergence",D46="Contradiction"),IF(G46="","Unresolved",IF(H46="","Reason missing","Calibrated")),"Agreement")))
A47: ="K5"&IF('00 Setup'!B20="",""," · "&'00 Setup'!B20) -> K5 | B47: C5 | C47: =IF('01 Rubric'!B12="","",'01 Rubric'!B12) -> Cash, treasury and working capital | D47: ='03 Divergence'!K47 | E47: ='03 Divergence'!H47 | F47: ='03 Divergence'!J47 | I47: =IF(D47="","",IF(D47="No evidence",0,IF(OR(D47="Divergence",D47="Contradiction"),IF(G47="",F47,G47),F47))) | J47: =IF(D47="","",IF(D47="No evidence","No evidence",IF(OR(D47="Divergence",D47="Contradiction"),IF(G47="","Unresolved",IF(H47="","Reason missing","Calibrated")),"Agreement")))
A48: ="K5"&IF('00 Setup'!B20="",""," · "&'00 Setup'!B20) -> K5 | B48: C6 | C48: =IF('01 Rubric'!B13="","",'01 Rubric'!B13) -> Systems, data and reporting tooling | D48: ='03 Divergence'!K48 | E48: ='03 Divergence'!H48 | F48: ='03 Divergence'!J48 | I48: =IF(D48="","",IF(D48="No evidence",0,IF(OR(D48="Divergence",D48="Contradiction"),IF(G48="",F48,G48),F48))) | J48: =IF(D48="","",IF(D48="No evidence","No evidence",IF(OR(D48="Divergence",D48="Contradiction"),IF(G48="","Unresolved",IF(H48="","Reason missing","Calibrated")),"Agreement")))
A49: ="K5"&IF('00 Setup'!B20="",""," · "&'00 Setup'!B20) -> K5 | B49: C7 | C49: =IF('01 Rubric'!B14="","",'01 Rubric'!B14) -> Team leadership and delegation | D49: ='03 Divergence'!K49 | E49: ='03 Divergence'!H49 | F49: ='03 Divergence'!J49 | I49: =IF(D49="","",IF(D49="No evidence",0,IF(OR(D49="Divergence",D49="Contradiction"),IF(G49="",F49,G49),F49))) | J49: =IF(D49="","",IF(D49="No evidence","No evidence",IF(OR(D49="Divergence",D49="Contradiction"),IF(G49="","Unresolved",IF(H49="","Reason missing","Calibrated")),"Agreement")))
A50: ="K5"&IF('00 Setup'!B20="",""," · "&'00 Setup'!B20) -> K5 | B50: C8 | C50: =IF('01 Rubric'!B15="","",'01 Rubric'!B15) -> Stakeholder communication and reporting | D50: ='03 Divergence'!K50 | E50: ='03 Divergence'!H50 | F50: ='03 Divergence'!J50 | I50: =IF(D50="","",IF(D50="No evidence",0,IF(OR(D50="Divergence",D50="Contradiction"),IF(G50="",F50,G50),F50))) | J50: =IF(D50="","",IF(D50="No evidence","No evidence",IF(OR(D50="Divergence",D50="Contradiction"),IF(G50="","Unresolved",IF(H50="","Reason missing","Calibrated")),"Agreement")))
A51: ="K5"&IF('00 Setup'!B20="",""," · "&'00 Setup'!B20) -> K5 | B51: C9 | C51: =IF('01 Rubric'!B16="","",'01 Rubric'!B16) -> Jurisdictional and regulatory exposure | D51: ='03 Divergence'!K51 | E51: ='03 Divergence'!H51 | F51: ='03 Divergence'!J51 | I51: =IF(D51="","",IF(D51="No evidence",0,IF(OR(D51="Divergence",D51="Contradiction"),IF(G51="",F51,G51),F51))) | J51: =IF(D51="","",IF(D51="No evidence","No evidence",IF(OR(D51="Divergence",D51="Contradiction"),IF(G51="","Unresolved",IF(H51="","Reason missing","Calibrated")),"Agreement")))
A52: ="K6"&IF('00 Setup'!B21="",""," · "&'00 Setup'!B21) -> K6 | B52: C1 | C52: =IF('01 Rubric'!B8="","",'01 Rubric'!B8) -> Technical accounting and IFRS application | D52: ='03 Divergence'!K52 | E52: ='03 Divergence'!H52 | F52: ='03 Divergence'!J52 | I52: =IF(D52="","",IF(D52="No evidence",0,IF(OR(D52="Divergence",D52="Contradiction"),IF(G52="",F52,G52),F52))) | J52: =IF(D52="","",IF(D52="No evidence","No evidence",IF(OR(D52="Divergence",D52="Contradiction"),IF(G52="","Unresolved",IF(H52="","Reason missing","Calibrated")),"Agreement")))
A53: ="K6"&IF('00 Setup'!B21="",""," · "&'00 Setup'!B21) -> K6 | B53: C2 | C53: =IF('01 Rubric'!B9="","",'01 Rubric'!B9) -> Financial reporting and close ownership | D53: ='03 Divergence'!K53 | E53: ='03 Divergence'!H53 | F53: ='03 Divergence'!J53 | I53: =IF(D53="","",IF(D53="No evidence",0,IF(OR(D53="Divergence",D53="Contradiction"),IF(G53="",F53,G53),F53))) | J53: =IF(D53="","",IF(D53="No evidence","No evidence",IF(OR(D53="Divergence",D53="Contradiction"),IF(G53="","Unresolved",IF(H53="","Reason missing","Calibrated")),"Agreement")))
A54: ="K6"&IF('00 Setup'!B21="",""," · "&'00 Setup'!B21) -> K6 | B54: C3 | C54: =IF('01 Rubric'!B10="","",'01 Rubric'!B10) -> Controls, compliance and audit readiness | D54: ='03 Divergence'!K54 | E54: ='03 Divergence'!H54 | F54: ='03 Divergence'!J54 | I54: =IF(D54="","",IF(D54="No evidence",0,IF(OR(D54="Divergence",D54="Contradiction"),IF(G54="",F54,G54),F54))) | J54: =IF(D54="","",IF(D54="No evidence","No evidence",IF(OR(D54="Divergence",D54="Contradiction"),IF(G54="","Unresolved",IF(H54="","Reason missing","Calibrated")),"Agreement")))
A55: ="K6"&IF('00 Setup'!B21="",""," · "&'00 Setup'!B21) -> K6 | B55: C4 | C55: =IF('01 Rubric'!B11="","",'01 Rubric'!B11) -> Planning, budgeting and forecasting | D55: ='03 Divergence'!K55 | E55: ='03 Divergence'!H55 | F55: ='03 Divergence'!J55 | I55: =IF(D55="","",IF(D55="No evidence",0,IF(OR(D55="Divergence",D55="Contradiction"),IF(G55="",F55,G55),F55))) | J55: =IF(D55="","",IF(D55="No evidence","No evidence",IF(OR(D55="Divergence",D55="Contradiction"),IF(G55="","Unresolved",IF(H55="","Reason missing","Calibrated")),"Agreement")))
A56: ="K6"&IF('00 Setup'!B21="",""," · "&'00 Setup'!B21) -> K6 | B56: C5 | C56: =IF('01 Rubric'!B12="","",'01 Rubric'!B12) -> Cash, treasury and working capital | D56: ='03 Divergence'!K56 | E56: ='03 Divergence'!H56 | F56: ='03 Divergence'!J56 | I56: =IF(D56="","",IF(D56="No evidence",0,IF(OR(D56="Divergence",D56="Contradiction"),IF(G56="",F56,G56),F56))) | J56: =IF(D56="","",IF(D56="No evidence","No evidence",IF(OR(D56="Divergence",D56="Contradiction"),IF(G56="","Unresolved",IF(H56="","Reason missing","Calibrated")),"Agreement")))
A57: ="K6"&IF('00 Setup'!B21="",""," · "&'00 Setup'!B21) -> K6 | B57: C6 | C57: =IF('01 Rubric'!B13="","",'01 Rubric'!B13) -> Systems, data and reporting tooling | D57: ='03 Divergence'!K57 | E57: ='03 Divergence'!H57 | F57: ='03 Divergence'!J57 | I57: =IF(D57="","",IF(D57="No evidence",0,IF(OR(D57="Divergence",D57="Contradiction"),IF(G57="",F57,G57),F57))) | J57: =IF(D57="","",IF(D57="No evidence","No evidence",IF(OR(D57="Divergence",D57="Contradiction"),IF(G57="","Unresolved",IF(H57="","Reason missing","Calibrated")),"Agreement")))
A58: ="K6"&IF('00 Setup'!B21="",""," · "&'00 Setup'!B21) -> K6 | B58: C7 | C58: =IF('01 Rubric'!B14="","",'01 Rubric'!B14) -> Team leadership and delegation | D58: ='03 Divergence'!K58 | E58: ='03 Divergence'!H58 | F58: ='03 Divergence'!J58 | I58: =IF(D58="","",IF(D58="No evidence",0,IF(OR(D58="Divergence",D58="Contradiction"),IF(G58="",F58,G58),F58))) | J58: =IF(D58="","",IF(D58="No evidence","No evidence",IF(OR(D58="Divergence",D58="Contradiction"),IF(G58="","Unresolved",IF(H58="","Reason missing","Calibrated")),"Agreement")))
A59: ="K6"&IF('00 Setup'!B21="",""," · "&'00 Setup'!B21) -> K6 | B59: C8 | C59: =IF('01 Rubric'!B15="","",'01 Rubric'!B15) -> Stakeholder communication and reporting | D59: ='03 Divergence'!K59 | E59: ='03 Divergence'!H59 | F59: ='03 Divergence'!J59 | I59: =IF(D59="","",IF(D59="No evidence",0,IF(OR(D59="Divergence",D59="Contradiction"),IF(G59="",F59,G59),F59))) | J59: =IF(D59="","",IF(D59="No evidence","No evidence",IF(OR(D59="Divergence",D59="Contradiction"),IF(G59="","Unresolved",IF(H59="","Reason missing","Calibrated")),"Agreement")))
A60: ="K6"&IF('00 Setup'!B21="",""," · "&'00 Setup'!B21) -> K6 | B60: C9 | C60: =IF('01 Rubric'!B16="","",'01 Rubric'!B16) -> Jurisdictional and regulatory exposure | D60: ='03 Divergence'!K60 | E60: ='03 Divergence'!H60 | F60: ='03 Divergence'!J60 | I60: =IF(D60="","",IF(D60="No evidence",0,IF(OR(D60="Divergence",D60="Contradiction"),IF(G60="",F60,G60),F60))) | J60: =IF(D60="","",IF(D60="No evidence","No evidence",IF(OR(D60="Divergence",D60="Contradiction"),IF(G60="","Unresolved",IF(H60="","Reason missing","Calibrated")),"Agreement")))
C62: Flagged cells | D62: =COUNTIF(D7:D60,"Divergence")+COUNTIF(D7:D60,"Contradiction") -> 0
C63: Calibrated | D63: =COUNTIF(J7:J60,"Calibrated") -> 0
C64: Unresolved | D64: =COUNTIF(J7:J60,"Unresolved") -> 0
C65: Reason missing | D65: =COUNTIF(J7:J60,"Reason missing") -> 0
C66: Calibrated score entered on an unflagged cell | D66: =SUMPRODUCT((G7:G60<>"")*(J7:J60<>"Calibrated")*(J7:J60<>"Reason missing")) -> 0

Sheet 05 Results
A1: CALIBRE BY DAFTAR
A2: 05 · Scores after calibration and the weighted result
A3: Entry order only. Never sort, colour or label finalists. The weighted result (0 to 100) is advisory: an input to the recommendation, not the recommendation.
A6: Ref | B6: Criterion | C6: Weight % | D6: ="K1"&IF('00 Setup'!B16="",""," · "&'00 Setup'!B16) -> K1 | E6: ="K2"&IF('00 Setup'!B17="",""," · "&'00 Setup'!B17) -> K2 | F6: ="K3"&IF('00 Setup'!B18="",""," · "&'00 Setup'!B18) -> K3 | G6: ="K4"&IF('00 Setup'!B19="",""," · "&'00 Setup'!B19) -> K4 | H6: ="K5"&IF('00 Setup'!B20="",""," · "&'00 Setup'!B20) -> K5 | I6: ="K6"&IF('00 Setup'!B21="",""," · "&'00 Setup'!B21) -> K6
A8: C1 | B8: =IF('01 Rubric'!B8="","",'01 Rubric'!B8) -> Technical accounting and IFRS application | C8: =IF('01 Rubric'!D8="","",'01 Rubric'!D8) -> 15 | D8: ='04 Calibration'!I7 | E8: ='04 Calibration'!I16 | F8: ='04 Calibration'!I25 | G8: ='04 Calibration'!I34 | H8: ='04 Calibration'!I43 | I8: ='04 Calibration'!I52
A9: C2 | B9: =IF('01 Rubric'!B9="","",'01 Rubric'!B9) -> Financial reporting and close ownership | C9: =IF('01 Rubric'!D9="","",'01 Rubric'!D9) -> 15 | D9: ='04 Calibration'!I8 | E9: ='04 Calibration'!I17 | F9: ='04 Calibration'!I26 | G9: ='04 Calibration'!I35 | H9: ='04 Calibration'!I44 | I9: ='04 Calibration'!I53
A10: C3 | B10: =IF('01 Rubric'!B10="","",'01 Rubric'!B10) -> Controls, compliance and audit readiness | C10: =IF('01 Rubric'!D10="","",'01 Rubric'!D10) -> 12 | D10: ='04 Calibration'!I9 | E10: ='04 Calibration'!I18 | F10: ='04 Calibration'!I27 | G10: ='04 Calibration'!I36 | H10: ='04 Calibration'!I45 | I10: ='04 Calibration'!I54
A11: C4 | B11: =IF('01 Rubric'!B11="","",'01 Rubric'!B11) -> Planning, budgeting and forecasting | C11: =IF('01 Rubric'!D11="","",'01 Rubric'!D11) -> 12 | D11: ='04 Calibration'!I10 | E11: ='04 Calibration'!I19 | F11: ='04 Calibration'!I28 | G11: ='04 Calibration'!I37 | H11: ='04 Calibration'!I46 | I11: ='04 Calibration'!I55
A12: C5 | B12: =IF('01 Rubric'!B12="","",'01 Rubric'!B12) -> Cash, treasury and working capital | C12: =IF('01 Rubric'!D12="","",'01 Rubric'!D12) -> 8 | D12: ='04 Calibration'!I11 | E12: ='04 Calibration'!I20 | F12: ='04 Calibration'!I29 | G12: ='04 Calibration'!I38 | H12: ='04 Calibration'!I47 | I12: ='04 Calibration'!I56
A13: C6 | B13: =IF('01 Rubric'!B13="","",'01 Rubric'!B13) -> Systems, data and reporting tooling | C13: =IF('01 Rubric'!D13="","",'01 Rubric'!D13) -> 10 | D13: ='04 Calibration'!I12 | E13: ='04 Calibration'!I21 | F13: ='04 Calibration'!I30 | G13: ='04 Calibration'!I39 | H13: ='04 Calibration'!I48 | I13: ='04 Calibration'!I57
A14: C7 | B14: =IF('01 Rubric'!B14="","",'01 Rubric'!B14) -> Team leadership and delegation | C14: =IF('01 Rubric'!D14="","",'01 Rubric'!D14) -> 10 | D14: ='04 Calibration'!I13 | E14: ='04 Calibration'!I22 | F14: ='04 Calibration'!I31 | G14: ='04 Calibration'!I40 | H14: ='04 Calibration'!I49 | I14: ='04 Calibration'!I58
A15: C8 | B15: =IF('01 Rubric'!B15="","",'01 Rubric'!B15) -> Stakeholder communication and reporting | C15: =IF('01 Rubric'!D15="","",'01 Rubric'!D15) -> 10 | D15: ='04 Calibration'!I14 | E15: ='04 Calibration'!I23 | F15: ='04 Calibration'!I32 | G15: ='04 Calibration'!I41 | H15: ='04 Calibration'!I50 | I15: ='04 Calibration'!I59
A16: C9 | B16: =IF('01 Rubric'!B16="","",'01 Rubric'!B16) -> Jurisdictional and regulatory exposure | C16: =IF('01 Rubric'!D16="","",'01 Rubric'!D16) -> 8 | D16: ='04 Calibration'!I15 | E16: ='04 Calibration'!I24 | F16: ='04 Calibration'!I33 | G16: ='04 Calibration'!I42 | H16: ='04 Calibration'!I51 | I16: ='04 Calibration'!I60
B17: Weighted result (advisory) | D17: =IF(COUNT(D8:D16)=0,"",SUMPRODUCT($C$8:$C$16,D8:D16)/5) | E17: =IF(COUNT(E8:E16)=0,"",SUMPRODUCT($C$8:$C$16,E8:E16)/5) | F17: =IF(COUNT(F8:F16)=0,"",SUMPRODUCT($C$8:$C$16,F8:F16)/5) | G17: =IF(COUNT(G8:G16)=0,"",SUMPRODUCT($C$8:$C$16,G8:G16)/5) | H17: =IF(COUNT(H8:H16)=0,"",SUMPRODUCT($C$8:$C$16,H8:H16)/5) | I17: =IF(COUNT(I8:I16)=0,"",SUMPRODUCT($C$8:$C$16,I8:I16)/5)
B18: Criteria with no evidence | D18: =IF(D17="","",COUNTIF('04 Calibration'!J7:J15,"No evidence")) | E18: =IF(E17="","",COUNTIF('04 Calibration'!J16:J24,"No evidence")) | F18: =IF(F17="","",COUNTIF('04 Calibration'!J25:J33,"No evidence")) | G18: =IF(G17="","",COUNTIF('04 Calibration'!J34:J42,"No evidence")) | H18: =IF(H17="","",COUNTIF('04 Calibration'!J43:J51,"No evidence")) | I18: =IF(I17="","",COUNTIF('04 Calibration'!J52:J60,"No evidence"))
B19: Unresolved cells | D19: =IF(D17="","",COUNTIF('04 Calibration'!J7:J15,"Unresolved")) | E19: =IF(E17="","",COUNTIF('04 Calibration'!J16:J24,"Unresolved")) | F19: =IF(F17="","",COUNTIF('04 Calibration'!J25:J33,"Unresolved")) | G19: =IF(G17="","",COUNTIF('04 Calibration'!J34:J42,"Unresolved")) | H19: =IF(H17="","",COUNTIF('04 Calibration'!J43:J51,"Unresolved")) | I19: =IF(I17="","",COUNTIF('04 Calibration'!J52:J60,"Unresolved"))
B20: Note | D20: =IF(D17="","",IF(D18>0,"Incomplete","")) | E20: =IF(E17="","",IF(E18>0,"Incomplete","")) | F20: =IF(F17="","",IF(F18>0,"Incomplete","")) | G20: =IF(G17="","",IF(G18>0,"Incomplete","")) | H20: =IF(H17="","",IF(H18>0,"Incomplete","")) | I20: =IF(I17="","",IF(I18>0,"Incomplete",""))
A22: Internal checks for the Verdict. Not for the client, and never shown as an order of finalists.
B23: Highest weighted result | C23: =IF(COUNT(D17:I17)=0,"",INDEX($D$6:$I$6,MATCH(MAX(D17:I17),D17:I17,0)))
B24: Its criteria scored 1 or 2 | C24: =IF(C23="","",SUMPRODUCT((INDEX($D$8:$I$16,0,MATCH(MAX(D17:I17),D17:I17,0))>0)*(INDEX($D$8:$I$16,0,MATCH(MAX(D17:I17),D17:I17,0))<=2)*($C$8:$C$16<>""))) | D24: A risk for section 07 of the Verdict. If the recommendation names a different finalist, section 08 needs a written job-related reason.

Sheet 06 Outcomes
A1: CALIBRE BY DAFTAR
A2: 06 · Outcome register
A3: Recorded against the role, by initials only. It is the only way Calibre can one day make a claim about itself.
A5: Candidate hired | E5: Start date
A7: Checkpoint | B7: Due | C7: Still in the seat? | D7: If not, why | E7: Manager satisfaction (1 to 5) | F7: Early performance concerns? | G7: One line | H7: Did the Verdict flag what later mattered? | I7: One line | J7: Change to the rubric or method
A8: 90 days | B8: =IF($F$5="","",$F$5+90)
A9: 180 days | B9: =IF($F$5="","",$F$5+180)
A10: 365 days | B10: =IF($F$5="","",$F$5+365)
